{"ts": 1784228885.678151, "discovered": 400, "prefiltered": 5, "channels": {"dexscreener_boosts": 16, "dexscreener_profiles": 12, "gecko_new_pools": 40, "gecko_trending": 20, "jupiter_recent": 30, "pumpfun_graduations": 321, "helius_new_pools": 1494}, "watchlist": 560, "candidates": [], "narratives": [{"narrative": "~aero", "strength": 0.977, "tokens": 36, "volume_h1": 801358.16, "median_h1_pct": 27.2}, {"narrative": "~dotty", "strength": 0.953, "tokens": 6, "volume_h1": 432307.45999999996, "median_h1_pct": 105.8}, {"narrative": "cat", "strength": 0.9, "tokens": 1192, "volume_h1": 7958181.56, "median_h1_pct": 0.0}, {"narrative": "~cash", "strength": 0.9, "tokens": 206, "volume_h1": 3623547.33, "median_h1_pct": 0.0}, {"narrative": "ai", "strength": 0.9, "tokens": 1429, "volume_h1": 7731577.64, "median_h1_pct": 0.0}, {"narrative": "animal-other", "strength": 0.9, "tokens": 305, "volume_h1": 983456.46, "median_h1_pct": 0.0}, {"narrative": "~gravewake", "strength": 0.9, "tokens": 24, "volume_h1": 1004263.15, "median_h1_pct": 0.0}, {"narrative": "~bull", "strength": 0.9, "tokens": 776, "volume_h1": 7201958.33, "median_h1_pct": 0.0}], "rejects": [{"snapshot": {"address": "DGHWbPJSPAWkGLQxipHwmG4e7pZBTVBeL3v8Ym7qm3Xy", "symbol": "CASHCOW", "name": "Cash Cow", "chain": "solana", "pair_address": "H4SyqeugGedaPENGGPCTzwRmjxbxZ4yLawVuidz9g2sp", "dex": "pumpswap", "price_usd": 0.0001462, "price_native": 1.933e-06, "liquidity_usd": 219484.11, "fdv_usd": 146278.0, "market_cap_usd": 146278.0, "volume_h1": 1905862.03, "volume_h24": 16707885.32, "price_change_m5": -0.57, "price_change_h1": -2.86, "price_change_h6": 189.0, "price_change_h24": 189.0, "buys_h1": 2147, "sells_h1": 1229, "buys_m5": 179, "sells_m5": 102, "pair_created_at": 1784209734.0, "fetched_at": 1784228882.4686348}, "reason": "safety: rug score 0.52 > 0.4"}, {"snapshot": {"address": "9cRCn9rGT8V2imeM2BaKs13yhMEais3ruM3rPvTGpump", "symbol": "ANSEM", "name": "The Black Bull", "chain": "solana", "pair_address": "FnzKY6x7entQ1eR3D225dQyT7ybfka4PskBMQhb8L3CC", "dex": "pumpswap", "price_usd": 0.2109, "price_native": 0.002785, "liquidity_usd": 2066146.09, "fdv_usd": 210895831.0, "market_cap_usd": 210895831.0, "volume_h1": 1745512.41, "volume_h24": 12623867.5, "price_change_m5": 0.26, "price_change_h1": -2.59, "price_change_h6": 17.28, "price_change_h24": 11.53, "buys_h1": 2549, "sells_h1": 2103, "buys_m5": 71, "sells_m5": 27, "pair_created_at": 1781643948.0, "fetched_at": 1784228885.359366}, "reason": "liquidity too high (not early)"}, {"snapshot": {"address": "G5iYscNofSyYbTqfLhojaFHz4KM5S5ipvzcmrBCQMEnn", "symbol": "CXMT", "name": "\u957f\u946b\u79d1\u6280", "chain": "solana", "pair_address": "ALUqpSGntKw5pZtqeLA2FdRnNLauhpKK8vGLD7Tc9GmW", "dex": "pumpswap", "price_usd": 8.896e-05, "price_native": 1.175e-06, "liquidity_usd": 112366.06, "fdv_usd": 88961.0, "market_cap_usd": 88961.0, "volume_h1": 1655185.87, "volume_h24": 7782134.91, "price_change_m5": 1.24, "price_change_h1": -1.79, "price_change_h6": 262.0, "price_change_h24": 262.0, "buys_h1": 3169, "sells_h1": 3170, "buys_m5": 258, "sells_m5": 258, "pair_created_at": 1784211906.0, "fetched_at": 1784228882.0630841}, "reason": "mcap 88,961 out of range"}, {"snapshot": {"address": "GVTgsov5kvJzmRvPah5bqPCTn3c6KzKZazf9BLBNwtww", "symbol": "BASE", "name": "Base_coin", "chain": "solana", "pair_address": "GrntHzzJqae3En2bPwmBqKYQz3zJ3rpXTEhrPT5VHytz", "dex": "pumpswap", "price_usd": 1.622e-05, "price_native": 2.144e-07, "liquidity_usd": 468917.1, "fdv_usd": 1622795.0, "market_cap_usd": 1622795.0, "volume_h1": 1496931.26, "volume_h24": 46810538.6, "price_change_m5": -0.51, "price_change_h1": 3.82, "price_change_h6": 53.17, "price_change_h24": 215.0, "buys_h1": 4914, "sells_h1": 3602, "buys_m5": 428, "sells_m5": 316, "pair_created_at": 1784195902.0, "fetched_at": 1784228884.933134}, "reason": "already pumped 215% in 24h"}, {"snapshot": {"address": "CbDNPQHGFeRwSxb4mzfL19o2J85m3DbFwiwr8dYu9sNU", "symbol": "ANSEM", "name": "The Black Bull", "chain": "solana", "pair_address": "HEt8oE4EB2TFc1m9EKdck2J2yZVCxkhhqbN7UeWwe4nQ", "dex": "pumpswap", "price_usd": 0.004464, "price_native": 5.901e-05, "liquidity_usd": 52730.1, "fdv_usd": 4464259.0, "market_cap_usd": 4464259.0, "volume_h1": 844578.75, "volume_h24": 3230317.3, "price_change_m5": 3.24, "price_change_h1": 60.28, "price_change_h6": 57850.0, "price_change_h24": 57850.0, "buys_h1": 1855, "sells_h1": 1855, "buys_m5": 160, "sells_m5": 160, "pair_created_at": 1784214810.0, "fetched_at": 1784228881.2277749}, "reason": "liq/mcap 1.2% < 10%"}, {"snapshot": {"address": "3sCAvRUZdijyVhMmmUP9L3okEHiw28XAafS7ZtWypump", "symbol": "Jimothy", "name": "Mutant creature Jimothy", "chain": "solana", "pair_address": "6jYdKQ2dQWSLa6YpnyQQpv6uuME4jty5DKVmK6xsLKPh", "dex": "pumpswap", "price_usd": 0.0002465, "price_native": 3.258e-06, "liquidity_usd": 37419.46, "fdv_usd": 246518.0, "market_cap_usd": 246518.0, "volume_h1": 528579.17, "volume_h24": 528579.17, "price_change_m5": 6.25, "price_change_h1": 368.0, "price_change_h6": 368.0, "price_change_h24": 368.0, "buys_h1": 12190, "sells_h1": 2128, "buys_m5": 959, "sells_m5": 161, "pair_created_at": 1784225373.0, "fetched_at": 1784228878.590092}, "reason": "already pumped 368% in 24h"}, {"snapshot": {"address": "B7xyju9AKh9nLiUdtarnAchj7FhRUbmEBiViMybbuFrF", "symbol": "EXT", "name": "Extended", "chain": "solana", "pair_address": "zrWsMTNB1KXwsrpxSzLnBE8uBxCrodzMKtommH9HhTS", "dex": "pumpswap", "price_usd": 1.05e-06, "price_native": 1.388e-08, "liquidity_usd": 45974.48, "fdv_usd": 105062.0, "market_cap_usd": 105062.0, "volume_h1": 456951.93, "volume_h24": 7663615.84, "price_change_m5": -0.24, "price_change_h1": 2.76, "price_change_h6": 63.55, "price_change_h24": 130.0, "buys_h1": 3607, "sells_h1": 1388, "buys_m5": 314, "sells_m5": 118, "pair_created_at": 1784204067.0, "fetched_at": 1784228883.2580638}, "reason": "safety: rug score 0.52 > 0.4"}, {"snapshot": {"address": "GigkxPr8A24kDqA7D67fT8X6XxEdeFNeoY4xscLXjsSU", "symbol": "BLOCK", "name": "MagicBloc", "chain": "solana", "pair_address": "5j46F6k8A8yNafiA4dSzPZmRLM1ohXyj8X3KP4iC1z3B", "dex": "pumpswap", "price_usd": 1.528e-06, "price_native": 2.02e-08, "liquidity_usd": 38354.37, "fdv_usd": 152883.0, "market_cap_usd": 152883.0, "volume_h1": 453862.78, "volume_h24": 6400114.7, "price_change_m5": 0.5, "price_change_h1": 3.5, "price_change_h6": 91.33, "price_change_h24": 346.0, "buys_h1": 3646, "sells_h1": 1365, "buys_m5": 313, "sells_m5": 119, "pair_created_at": 1784204380.0, "fetched_at": 1784228883.2579489}, "reason": "already pumped 346% in 24h"}, {"snapshot": {"address": "HNK3kAaR9ArLjbZjCQyWLbziX5tcjqpb8XLiXfY5yuQN", "symbol": "PREDICT", "name": "predictdotfun", "chain": "solana", "pair_address": "9nDpQUNcWupDPqTs9EswS4K3jeysYA1Z6BhaQwZ51sL2", "dex": "pumpswap", "price_usd": 1.401e-06, "price_native": 1.852e-08, "liquidity_usd": 36890.22, "fdv_usd": 140146.0, "market_cap_usd": 140146.0, "volume_h1": 450587.36, "volume_h24": 6382367.17, "price_change_m5": -0.75, "price_change_h1": 2.01, "price_change_h6": 69.86, "price_change_h24": 306.0, "buys_h1": 3587, "sells_h1": 1357, "buys_m5": 311, "sells_m5": 119, "pair_created_at": 1784204249.0, "fetched_at": 1784228883.2580411}, "reason": "already pumped 306% in 24h"}, {"snapshot": {"address": "AaeRR63ihifBE6h9TVH9LV8tnN6u68ewHXHrJoRP5DZJ", "symbol": "GHOSTI", "name": "Ghosti", "chain": "solana", "pair_address": "8zRB2YV5u5eXwkkQQsegXwmQyqfehbsEV2SnmmrXVUfK", "dex": "pumpswap", "price_usd": 0.0002697, "price_native": 3.563e-06, "liquidity_usd": 40146.2, "fdv_usd": 269784.0, "market_cap_usd": 269784.0, "volume_h1": 380661.82, "volume_h24": 1277729.8, "price_change_m5": -8.37, "price_change_h1": -25.63, "price_change_h6": 553.0, "price_change_h24": 553.0, "buys_h1": 4485, "sells_h1": 3036, "buys_m5": 155, "sells_m5": 69, "pair_created_at": 1784223825.0, "fetched_at": 1784228885.359537}, "reason": "already pumped 553% in 24h"}, {"snapshot": {"address": "HHpUt97nkMypgZbV9X7a6TdkjaBW7b6JfVcYAqsmk8kA", "symbol": "ANSEM", "name": "The Black Bull", "chain": "solana", "pair_address": "4BSvAgiRQZBHcCNk47wSo8y4tQwsRKJV27UAhyeVeCKt", "dex": "pumpswap", "price_usd": 0.0001031, "price_native": 1.362e-06, "liquidity_usd": 33456.7, "fdv_usd": 103108.0, "market_cap_usd": 103108.0, "volume_h1": 246999.28, "volume_h24": 1089467.07, "price_change_m5": 30.59, "price_change_h1": 107.0, "price_change_h6": 6293.0, "price_change_h24": 6293.0, "buys_h1": 1040, "sells_h1": 1008, "buys_m5": 90, "sells_m5": 87, "pair_created_at": 1784212343.0, "fetched_at": 1784228882.063023}, "reason": "already pumped 6293% in 24h"}, {"snapshot": {"address": "E7vTVLLaxV3y68cpnDx2Q7ExeznhWgJKwPziKDsrpump", "symbol": "HOMIE", "name": "Welcome Back Homie", "chain": "solana", "pair_address": "5fg5azit5ed8PaZ12vdtTTMGXw5moNsutYXJWA2w6qDY", "dex": "pumpswap", "price_usd": 0.0003259, "price_native": 4.305e-06, "liquidity_usd": 46866.34, "fdv_usd": 325969.0, "market_cap_usd": 325969.0, "volume_h1": 150865.08, "volume_h24": 3264394.27, "price_change_m5": -3.78, "price_change_h1": -14.64, "price_change_h6": -59.33, "price_change_h24": 846.0, "buys_h1": 893, "sells_h1": 1586, "buys_m5": 58, "sells_m5": 108, "pair_created_at": 1784179220.0, "fetched_at": 1784228885.359447}, "reason": "already pumped 846% in 24h"}, {"snapshot": {"address": "3WPyjiX8MeLvBTtN862vnPcRyiirC6g8Xfn6ZZgspump", "symbol": "NGMI", "name": "The Crypto Trail", "chain": "solana", "pair_address": "8CLY8GMfuiPFKKRw5NywN7S1xm1qsZi2MQqUHLy42tp", "dex": "pumpswap", "price_usd": 7.43e-06, "price_native": 9.814e-08, "liquidity_usd": 6367.74, "fdv_usd": 7430.0, "market_cap_usd": 7430.0, "volume_h1": 149138.58, "volume_h24": 149138.58, "price_change_m5": 4.06, "price_change_h1": -76.14, "price_change_h6": -76.14, "price_change_h24": -76.14, "buys_h1": 2120, "sells_h1": 1655, "buys_m5": 2, "sells_m5": 3, "pair_created_at": 1784225827.0, "fetched_at": 1784228879.038836}, "reason": "liquidity 6,368 < 30,000"}, {"snapshot": {"address": "B4ptaVsUe6YbtBwAS38WFeweSrVNfQLCcj9JRrtjU8vn", "symbol": "SOLdiers", "name": "SOLdiers", "chain": "solana", "pair_address": "B4JM2z5DAqNCJtSFm4F8v5pc88KA8Fk3oyCSwEfsq9bR", "dex": "pumpswap", "price_usd": 0.001199, "price_native": 1.584e-05, "liquidity_usd": 123997.43, "fdv_usd": 1199496.0, "market_cap_usd": 1199496.0, "volume_h1": 140802.81, "volume_h24": 4796335.82, "price_change_m5": 2.89, "price_change_h1": 1.4, "price_change_h6": -7.57, "price_change_h24": -55.48, "buys_h1": 899, "sells_h1": 743, "buys_m5": 26, "sells_m5": 35, "pair_created_at": 1784122840.0, "fetched_at": 1784228885.3593879}, "reason": "safety: LP locked only 0%"}, {"snapshot": {"address": "7tUhzZozsDcZJ5mxUqShaxhJDdCDUj7FzUDTVv9Ypump", "symbol": "ALTIMA", "name": "Gently Used Nissan", "chain": "solana", "pair_address": "6hQ9L8ngfDK5JfT4v9WrxrRD8BQDz8HPNB72cvLJdyZT", "dex": "pumpswap", "price_usd": 3.654e-06, "price_native": 4.826e-08, "liquidity_usd": 4433.06, "fdv_usd": 3654.0, "market_cap_usd": 3654.0, "volume_h1": 137988.25, "volume_h24": 137988.25, "price_change_m5": -37.63, "price_change_h1": -87.7, "price_change_h6": -87.7, "price_change_h24": -87.7, "buys_h1": 2704, "sells_h1": 2091, "buys_m5": 24, "sells_m5": 39, "pair_created_at": 1784226891.0, "fetched_at": 1784228878.5901031}, "reason": "liquidity 4,433 < 30,000"}, {"snapshot": {"address": "CFPkPq1eYPR8GLzEo59wUbbMioX4bshaTQiSGzTSpump", "symbol": "MENSA", "name": "The Black Table", "chain": "solana", "pair_address": "E8RJG3srQBiSFMxDwrKG2DkwpWGyK7UYcFjkaTs9tbrS", "dex": "pumpswap", "price_usd": 0.003299, "price_native": 4.357e-05, "liquidity_usd": 184825.79, "fdv_usd": 3299939.0, "market_cap_usd": 3299939.0, "volume_h1": 113288.38, "volume_h24": 663851.48, "price_change_m5": -0.7, "price_change_h1": 8.2, "price_change_h6": 103.0, "price_change_h24": 80.9, "buys_h1": 407, "sells_h1": 537, "buys_m5": 20, "sells_m5": 18, "pair_created_at": 1782959359.0, "fetched_at": 1784228885.359514}, "reason": "liq/mcap 5.6% < 10%"}, {"snapshot": {"address": "DdPrHYqM8Ueovnk9kAnAgoGhswkuaTqmxcoZzU3Zpump", "symbol": "manlet", "name": "manlet", "chain": "solana", "pair_address": "8qDidAKuyNYKaR4dh2ZFZZVG5gBTUfyJcwQPgwt9FS1Y", "dex": "pumpswap", "price_usd": 0.001354, "price_native": 1.789e-05, "liquidity_usd": 138080.91, "fdv_usd": 1353027.0, "market_cap_usd": 1353027.0, "volume_h1": 97746.25, "volume_h24": 492142.69, "price_change_m5": -6.42, "price_change_h1": -0.58, "price_change_h6": 32.56, "price_change_h24": 49.02, "buys_h1": 484, "sells_h1": 439, "buys_m5": 24, "sells_m5": 11, "pair_created_at": 1782772288.0, "fetched_at": 1784228885.3596249}, "reason": "too old (405h)"}, {"snapshot": {"address": "HVRtNeFPrDcAA9Yu3WrTEdCsTLGJiYDiQbqjg3efpump", "symbol": "CUBEMAN", "name": "CUBEMAN", "chain": "solana", "pair_address": "4z3ZkJiksBXGr7PVkfSJBuK2GmkHmTTfaGHmGWPAgo8D", "dex": "pumpswap", "price_usd": 0.0008615, "price_native": 1.137e-05, "liquidity_usd": 71644.19, "fdv_usd": 861513.0, "market_cap_usd": 861513.0, "volume_h1": 82616.02, "volume_h24": 1499069.23, "price_change_m5": -2.52, "price_change_h1": -15.33, "price_change_h6": 8.22, "price_change_h24": 2543.0, "buys_h1": 708, "sells_h1": 404, "buys_m5": 55, "sells_m5": 31, "pair_created_at": 1784178477.0, "fetched_at": 1784228885.359465}, "reason": "liq/mcap 8.3% < 10%"}, {"snapshot": {"address": "4ko5tSr5o3H4v1sFtjTSd9MPUW7yx5AFCpkNPoL6pump", "symbol": "febu", "name": "febu", "chain": "solana", "pair_address": "68nVMrVPyxGJGbGH2P92E93SYhJcbe6QociZrqoqdjcB", "dex": "pumpswap", "price_usd": 0.001501, "price_native": 1.981e-05, "liquidity_usd": 147131.3, "fdv_usd": 1501022.0, "market_cap_usd": 1501022.0, "volume_h1": 68103.33, "volume_h24": 1094916.69, "price_change_m5": -0.41, "price_change_h1": -4.91, "price_change_h6": -12.13, "price_change_h24": -20.4, "buys_h1": 524, "sells_h1": 287, "buys_m5": 14, "sells_m5": 4, "pair_created_at": 1783549044.0, "fetched_at": 1784228885.359495}, "reason": "liq/mcap 9.8% < 10%"}, {"snapshot": {"address": "3393qwcHRJGTbhRqwTrU9i2CMAFJBa1JJVBJQUCipump", "symbol": "SOLFER", "name": "SOLFER", "chain": "solana", "pair_address": "9f6homuozRakT51y7iMkvqx9n6MCFp3aTdfvum5AEKd", "dex": "pumpswap", "price_usd": 1.394e-06, "price_native": 1.839e-08, "liquidity_usd": 2745.9, "fdv_usd": 1394.0, "market_cap_usd": 1394.0, "volume_h1": 63784.74, "volume_h24": 63784.74, "price_change_m5": 0.0, "price_change_h1": -95.63, "price_change_h6": -95.63, "price_change_h24": -95.63, "buys_h1": 472, "sells_h1": 487, "buys_m5": 0, "sells_m5": 0, "pair_created_at": 1784226068.0, "fetched_at": 1784228879.03881}, "reason": "liquidity 2,746 < 30,000"}, {"snapshot": {"address": "He6pECrSVi123qabQJRiGEonMbBZ7e8PZ9NmUxKqpump", "symbol": "bet", "name": "aight bet", "chain": "solana", "pair_address": "EhGMAn1uEm5yPAFXPHG5HBZoPzQxvskhuCeUCg7r7Xt7", "dex": "pumpswap", "price_usd": 0.0001778, "price_native": 2.349e-06, "liquidity_usd": 34109.13, "fdv_usd": 177797.0, "market_cap_usd": 177797.0, "volume_h1": 63203.37, "volume_h24": 1533673.19, "price_change_m5": 9.47, "price_change_h1": 91.87, "price_change_h6": -18.99, "price_change_h24": 460.0, "buys_h1": 567, "sells_h1": 565, "buys_m5": 41, "sells_m5": 19, "pair_created_at": 1784183210.0, "fetched_at": 1784228885.3594759}, "reason": "already pumped 460% in 24h"}, {"snapshot": {"address": "CARDSccUMFKoPRZxt5vt3ksUbxEFEcnZ3H2pd3dKxYjp", "symbol": "CARDS", "name": "Collector Crypt", "chain": "solana", "pair_address": "HnhpJPJgBG2KwniMTNW8cVBHvk1hFog3RC3kjnyc23tD", "dex": "raydium", "price_usd": 0.1557, "price_native": 0.1557, "liquidity_usd": 2622312.28, "fdv_usd": 311595434.0, "market_cap_usd": 40126050.0, "volume_h1": 61706.65, "volume_h24": 926898.71, "price_change_m5": 0.07, "price_change_h1": 1.49, "price_change_h6": 2.27, "price_change_h24": -4.18, "buys_h1": 65, "sells_h1": 54, "buys_m5": 1, "sells_m5": 1, "pair_created_at": 1756493686.0, "fetched_at": 1784228885.648226}, "reason": "liquidity too high (not early)"}, {"snapshot": {"address": "2T5KFHjGtXobFHHR4tN3ThrP5hR3FMZxuAQCe461pump", "symbol": "ROBIN", "name": "Robin Hood", "chain": "solana", "pair_address": "ArXe1mFoVaGQxwDcVDiVRDHbKbehs2taqhNGiRshzJXb", "dex": "pumpswap", "price_usd": 1.08e-05, "price_native": 1.428e-07, "liquidity_usd": 7609.88, "fdv_usd": 10809.0, "market_cap_usd": 10809.0, "volume_h1": 61040.8, "volume_h24": 61040.8, "price_change_m5": -70.06, "price_change_h1": -65.77, "price_change_h6": -65.77, "price_change_h24": -65.77, "buys_h1": 1161, "sells_h1": 944, "buys_m5": 942, "sells_m5": 782, "pair_created_at": 1784228542.0, "fetched_at": 1784228879.038752}, "reason": "liquidity 7,610 < 30,000"}, {"snapshot": {"address": "Ge87EtsjwRQbHaqQmKRno69RFTwh9bfSsm99XNxTpump", "symbol": "Jimothy", "name": "Jimothy The Raccoon", "chain": "solana", "pair_address": "5PGhKctym6odbHGo2tKMST2AjmJsb2uZBQrKkn4ZuFT5", "dex": "pumpswap", "price_usd": 0.0001571, "price_native": 2.075e-06, "liquidity_usd": 31095.13, "fdv_usd": 157161.0, "market_cap_usd": 157161.0, "volume_h1": 60499.43, "volume_h24": 833310.08, "price_change_m5": 0.88, "price_change_h1": 7.61, "price_change_h6": 84.01, "price_change_h24": 402.0, "buys_h1": 522, "sells_h1": 529, "buys_m5": 19, "sells_m5": 23, "pair_created_at": 1784196945.0, "fetched_at": 1784228885.359582}, "reason": "already pumped 402% in 24h"}, {"snapshot": {"address": "G9j8WWDeJXZdvwQgP82ooDuHmpc3Gy8NCSins71Lpump", "symbol": "BULLCAT", "name": "The Bull Cat", "chain": "solana", "pair_address": "HuqmPUBBdq8w56Y6WGd8LiMbf4zgYXS2ACzLZs8MYLna", "dex": "pumpswap", "price_usd": 0.001153, "price_native": 1.523e-05, "liquidity_usd": 91613.33, "fdv_usd": 1153211.0, "market_cap_usd": 1153211.0, "volume_h1": 57715.52, "volume_h24": 1150385.47, "price_change_m5": 2.59, "price_change_h1": 23.64, "price_change_h6": 7.23, "price_change_h24": 0.58, "buys_h1": 531, "sells_h1": 970, "buys_m5": 29, "sells_m5": 52, "pair_created_at": 1784050150.0, "fetched_at": 1784228885.3593972}, "reason": "liq/mcap 7.9% < 10%"}], "mode": "paper", "status": {"equity": 1000.0, "cash": 1000.0, "starting_cash": 1000.0, "wins": 0, "losses": 0, "fees": 0.0, "killed": false, "halted_for_day": false}, "positions": []}