{"ts": 1784256259.5526662, "discovered": 491, "prefiltered": 1, "channels": {"dexscreener_boosts": 17, "dexscreener_profiles": 17, "gecko_new_pools": 40, "gecko_trending": 0, "jupiter_recent": 30, "pumpfun_graduations": 49, "helius_new_pools": 0}, "watchlist": 455, "candidates": [], "narratives": [{"narrative": "~chyna", "strength": 1.0, "tokens": 9, "volume_h1": 876516.47, "median_h1_pct": 50.8, "members": [{"address": "2E1bcZmYuNy7fbfwJzcJGT578PhBJaJNqQ7PwwX7ZAiZ", "symbol": "CHYNA", "volume_h1": 296818.88, "price_change_h1": 596.0}, {"address": "DtAvZU6K4bitFevYXPxwD929myw2PbvJbJPeMJjnsQ7W", "symbol": "CHYNA", "volume_h1": 289017.55, "price_change_h1": 139.0}, {"address": "8pStW6495TdRFHrf5Jc1cJgLLqYLMPJqXgXbmbbtB371", "symbol": "CHYNA", "volume_h1": 167071.7, "price_change_h1": 316.0}, {"address": "6Un7z4jcwFKyZoAAevBfZP3MVqn8iFgFKe7g5enB78Zz", "symbol": "CHYNA", "volume_h1": 47383.35, "price_change_h1": 50.77}, {"address": "86KUvpbqZZEPf2X1raWa5D3K42KAj4GYjX6NZs1Lpump", "symbol": "CHYNA", "volume_h1": 42683.85, "price_change_h1": 114.0}, {"address": "731Tbo2cfcVaB64mhWXVj28LvmVWRcT38oYpkGx5i8JL", "symbol": "CHYNA", "volume_h1": 26587.81, "price_change_h1": 28.6}, {"address": "8nDhqxuwtEpUz5GK3fdWEpyJFtV3cGdq27PBnESRVvba", "symbol": "CHYNA", "volume_h1": 3980.23, "price_change_h1": -26.13}, {"address": "5QRPcuNeFv7qXvZgFf34Q5Yv6K5co4urqboV9yLQpump", "symbol": "CHYNA", "volume_h1": 2487.38, "price_change_h1": -12.27}, {"address": "2P7U4JG5cdwFEL1WRBot4TsWzGuPntXuGFdbwpCspump", "symbol": "chyna", "volume_h1": 485.72, "price_change_h1": -6.53}]}, {"narrative": "~forge", "strength": 0.96, "tokens": 5, "volume_h1": 442421.74, "median_h1_pct": 70.0, "members": [{"address": "BQK9FSFEuj7ibuT6VLnZGUe5NWRDnKCwnqQvxBzCJs2K", "symbol": "FORGE", "volume_h1": 272406.76, "price_change_h1": 70.03}, {"address": "FmVtrnVsMLgpZhxxoTmh7MH43mon4jzpU5G4HzSvHGcf", "symbol": "FORGE", "volume_h1": 156985.79, "price_change_h1": 348.0}, {"address": "RPC8MbAndTBJ56nT25GkD7ZT38xsKjD6Ybo94HHJggF", "symbol": "FORGE", "volume_h1": 12091.7, "price_change_h1": 216.0}, {"address": "CcHKJnYvXwvKMqs1TTsKM4kifjJUW6bE7juvGtgPFFCi", "symbol": "FORGE", "volume_h1": 933.55, "price_change_h1": 14.31}, {"address": "6qPtgYEQweE53bGcNJLB8FKfxjqXSg1GmUFieJEgpump", "symbol": "FORGE", "volume_h1": 3.94, "price_change_h1": -0.68}]}, {"narrative": "cat", "strength": 0.9, "tokens": 106, "volume_h1": 3618537.59, "median_h1_pct": -3.2, "members": [{"address": "5yBMRg1GttnPRR5X7xZw7Ap8L77YJ1EKi11VSbmyncyQ", "symbol": "ASHCAT", "volume_h1": 876656.91, "price_change_h1": 472.0}, {"address": "7isZrjW57hUMpZbmcGEfBmopXArG2y1j5ueo5Q3eY13o", "symbol": "blepcat", "volume_h1": 663862.1, "price_change_h1": 1071.0}, {"address": "EGSJ5fUBCxzjKbYGbtF1GoWaK42HHTnv73zGwhqQdBqe", "symbol": "blepcat", "volume_h1": 318382.9, "price_change_h1": 74.08}, {"address": "J9Si9Ng52fMtQHreEig3QuUAEkQ3rVLh26hHohjHutq", "symbol": "WorldCat", "volume_h1": 292371.06, "price_change_h1": 427.0}, {"address": "EeeaQk7P98H2BHRXjdKJ49VTVNhWfRPz4YW2BbpKbosn", "symbol": "blepcat", "volume_h1": 288147.7, "price_change_h1": 496.0}, {"address": "8aJCYw4MUpk3BB18PS8wHrianmeFaDvvR9atwu6AdJ2u", "symbol": "blepcat", "volume_h1": 279011.61, "price_change_h1": 151.0}, {"address": "DnjevYJmKxE3eMaQc5QDrV82jAjpAp9y3ducjnomFwnp", "symbol": "blepcat", "volume_h1": 167953.18, "price_change_h1": 283.0}, {"address": "AWVkDL546FxuZD3nmLvgMm7db1w18cCjVNGqsS1bnDLR", "symbol": "blepcat", "volume_h1": 138979.66, "price_change_h1": 106.0}, {"address": "BBFGKB42V9kaSC82u5wLEydWtvmfihwvk2uKxU7Kme13", "symbol": "WorldCat", "volume_h1": 110209.06, "price_change_h1": 95.7}, {"address": "Gd321brJ2BHTDdmBPFw6PPJdM1MSihGEBSR5VzHXgjfy", "symbol": "blepcat", "volume_h1": 103507.95, "price_change_h1": 253.0}, {"address": "CRbhNBH64AQgRENMtAkLYFiQjrycbKRNzDjKEqhLpump", "symbol": "blepcat", "volume_h1": 62427.15, "price_change_h1": 6.47}, {"address": "87GehK2G6pmZbuMWJNKGXxwRCGrpZkRN8ZsLMfsQpump", "symbol": "DEPRIVEDCAT", "volume_h1": 26797.04, "price_change_h1": 12.08}, {"address": "8vHrrggGUJrDN21KkJ492uy3NwXqDVuP5JJqeQhy5W9C", "symbol": "ASHCAT", "volume_h1": 26372.66, "price_change_h1": 409.0}, {"address": "HXeYJqy5sQHBoDzhTjj6hRfoAGZvLQEb1BU1hN6SQgBi", "symbol": "BlazerCat", "volume_h1": 20170.66, "price_change_h1": 912.0}, {"address": "B6f27ETGcjgGNB1fqULJbXVmw9FnL8HgBp7R83hmpump", "symbol": "drooling", "volume_h1": 19499.92, "price_change_h1": 18.66}]}, {"narrative": "~bull", "strength": 0.9, "tokens": 162, "volume_h1": 2592088.39, "median_h1_pct": -1.4, "members": [{"address": "D4g5D6qzU6BGar2zGs34cLTEDv4x9314woxq9dCTxgFD", "symbol": "BullRock", "volume_h1": 310602.79, "price_change_h1": 393.0}, {"address": "8YR2LD8RRAxqKgeznmZYZsfAYikWzNxjSs8FajBsEYQS", "symbol": "LASTBULL", "volume_h1": 295114.43, "price_change_h1": 109.0}, {"address": "AWxckvLtck2vqygtHMCkUj9S7k4xwkJ863vaXAe7cJVk", "symbol": "GlitchBull", "volume_h1": 284787.96, "price_change_h1": 468.0}, {"address": "4igWj4rm3GfsFVvHV6V9EyZdbSVpvcX6nKinXUJAC1TJ", "symbol": "SUNSEM", "volume_h1": 274791.2, "price_change_h1": 86.65}, {"address": "9cRCn9rGT8V2imeM2BaKs13yhMEais3ruM3rPvTGpump", "symbol": "ANSEM", "volume_h1": 224541.28, "price_change_h1": -3.14}, {"address": "5p9wjvxvrppxFnDcsyxQagH6UcZTgGsZSbwLgTnvEGvh", "symbol": "SUNSEM", "volume_h1": 183428.69, "price_change_h1": 335.0}, {"address": "BKDZn2FiLwPDZr33g19eaDL2JPzVL5Hw3pNjzFvmdFNg", "symbol": "GlitchBull", "volume_h1": 175537.13, "price_change_h1": 347.0}, {"address": "jP6Nto8Puciw3hr2Lx9tFFrtbKDBK7NgNf3BshpXUW6", "symbol": "LASTBULL", "volume_h1": 173761.0, "price_change_h1": 339.0}, {"address": "48bRSQqHphm8iSfWFCDG8XN2cg6ak11TLnadU1PETLc1", "symbol": "BLACKBULL", "volume_h1": 161299.06, "price_change_h1": 330.0}, {"address": "7V6Sk63y8Rr1MvcN5mYNp61wgFhy4EeQg5gUASk9pump", "symbol": "HBULL", "volume_h1": 69896.61, "price_change_h1": -2.2}, {"address": "FpRcMwk3zv3DtwW77TwiGbvc3CaYt3EPrbNayfcpump", "symbol": "SUNSEM", "volume_h1": 55801.47, "price_change_h1": -95.47}, {"address": "EnenoFKRiyo2mvQeh8dSYS6VMYrqqkbi3rH37mcPpump", "symbol": "GlitchBull", "volume_h1": 49630.05, "price_change_h1": 933.0}, {"address": "6rSbf8T72z7AhVU11WR4oFg2FCFeJ6koYAS1ht68pump", "symbol": "BullRock", "volume_h1": 38851.58, "price_change_h1": -0.76}, {"address": "PdhB7EjbdypRg6huVrEoCxbLzeBRYejFnduicqkpump", "symbol": "BLACKBULL", "volume_h1": 33913.94, "price_change_h1": -93.35}, {"address": "GSFHexN41sc6BQuVmwEEkUZY7yAfb3EgaucG5rk3mvL8", "symbol": "SUNSEM", "volume_h1": 23585.85, "price_change_h1": 198.0}]}, {"narrative": "~cash", "strength": 0.9, "tokens": 13, "volume_h1": 2713187.8499999996, "median_h1_pct": 0.0, "members": [{"address": "Hwi9LHXUkzM8sA8TRP3WZqybYiMJNFhutQBNRHpPkG9A", "symbol": "CASHCOW", "volume_h1": 2216729.03, "price_change_h1": 48.96}, {"address": "D6ytjMdBBPoV8nsRHJhvrkpwF7sgVBYd7PufkRHNpump", "symbol": "CASHCOW", "volume_h1": 223699.17, "price_change_h1": -5.38}, {"address": "J968L8NU6vHjXeGSWMV9QKRARzQhGBa3Fm7QdEa2QJqk", "symbol": "CASHCOW", "volume_h1": 148426.29, "price_change_h1": 307.0}, {"address": "AWJkSP77HTYnWyWiBfRoK5nurwP4ApVw1YeEugmepump", "symbol": "CASHGOAT", "volume_h1": 106986.84, "price_change_h1": 115.0}, {"address": "8CduZyZw8dXZ3uVsC2i97ai47P8jSxr6myFyFDTXpump", "symbol": "CASHWOJAK", "volume_h1": 10816.23, "price_change_h1": 271.0}, {"address": "62t4NN8ACBPucosnefcnRhu5xkrTgw1t6VCfkUYHbonk", "symbol": "CASHGOAT", "volume_h1": 2363.27, "price_change_h1": 11.04}, {"address": "7HJdNKQTAa3SwpCGDniuMnTpxisMSGVSGudBesTxpump", "symbol": "CASH_C0W_", "volume_h1": 1376.44, "price_change_h1": -93.54}, {"address": "7YwWZMp24Ddr9ahPCSaDbYN2fzsuYFULhUwH8edVMuJy", "symbol": "\u3164", "volume_h1": 1051.99, "price_change_h1": 0.0}, {"address": "FBnmgkRnkZvs6xo8MxmgmCWGBZduE6Zub2jKzneNK4ha", "symbol": "m\u0254", "volume_h1": 1041.09, "price_change_h1": 0.0}, {"address": "Gs7EKK3Sf46TsmBsCA6YwgFmFY3tvKi5nHp8A2jypump", "symbol": "CASHGIRL", "volume_h1": 267.32, "price_change_h1": 0.01}, {"address": "Ezxn7QHYStvLSdfphx53MnVJBqq8JKHogNjmqzU5pump", "symbol": "CashGoat", "volume_h1": 228.6, "price_change_h1": -0.04}, {"address": "EHrb3YJr5TsmJSz1sWLRZu27iy9pgHQ6m7srvGNbpump", "symbol": "CashHog", "volume_h1": 115.92, "price_change_h1": -1.38}, {"address": "HYivnmSkyxCJNLRPS7rkZTbD49d73LBrC6VJTr1Apump", "symbol": "$CASHBAH", "volume_h1": 85.66, "price_change_h1": 0.49}]}, {"narrative": "ai", "strength": 0.9, "tokens": 161, "volume_h1": 746817.92, "median_h1_pct": -0.1, "members": [{"address": "GjvVu8U71zWptAxG8PgyYFk1Cy9y3k3qXs96tzmh8op9", "symbol": "AAIF", "volume_h1": 207883.4, "price_change_h1": 59249.0}, {"address": "2agcQWJftYzYWJNDW4BPok1RKL1xVqpDJtT4SSVVpump", "symbol": "CS", "volume_h1": 107417.72, "price_change_h1": -12.34}, {"address": "61V8vBaqAGMpgDQi4JcAwo1dmBGHsyhzodcPqnEVpump", "symbol": "arc", "volume_h1": 46589.95, "price_change_h1": -0.8}, {"address": "5Akc2FyV1MXQ1bdWFPAYyYXLyJkG6eRvAAPRWY1CK1kU", "symbol": "AppleAI", "volume_h1": 40378.1, "price_change_h1": 12562.0}, {"address": "He6pECrSVi123qabQJRiGEonMbBZ7e8PZ9NmUxKqpump", "symbol": "bet", "volume_h1": 38907.69, "price_change_h1": -21.67}, {"address": "HrNuDLvwQhWb4u1ynAHWF675ZPPWVsyBFoSwdsqebonk", "symbol": "NYPDR", "volume_h1": 38136.13, "price_change_h1": 114.0}, {"address": "BNGq6WsDCEBFVwv3Twm7KAFy3F3MXM8B2wuBQBKpNoyW", "symbol": "AAIF", "volume_h1": 36595.52, "price_change_h1": 35007.0}, {"address": "7RMg1HAhjFKhbSZS19FdHWZRG8pVBoZDU2nERiWGpump", "symbol": "ITSC", "volume_h1": 32679.41, "price_change_h1": 112.0}, {"address": "ETrFbNgEEKA2DdyayfjbmNk5MZRPStbcdY1cgFeb9KgJ", "symbol": "bet", "volume_h1": 27985.84, "price_change_h1": 39035.0}, {"address": "HNg5PYJmtqcmzXrv6S9zP1CDKk5BgDuyFBxbvNApump", "symbol": "ALCH", "volume_h1": 18476.84, "price_change_h1": -2.06}, {"address": "H5pDHXFtJ8ACZ6958L8RYqxgKnx7aG7YRcA5QkumBAGS", "symbol": "DAFFAL", "volume_h1": 18140.46, "price_change_h1": -95.48}, {"address": "GkGD3ZQsVnfqwHUq2co4AB2LU3too5dzTFgzVpDxbonk", "symbol": "OJPCHA", "volume_h1": 17861.87, "price_change_h1": 60.79}, {"address": "7duWKifTGzoMwywDQmSGPmJhDDxCMNVuAq48x1L3QqpG", "symbol": "CS", "volume_h1": 13676.65, "price_change_h1": 425.0}, {"address": "3v2ekTxcn6voD4RDzhwaf5z1VXFxGBxoUKEWZRfBpump", "symbol": "YUKI", "volume_h1": 12297.55, "price_change_h1": -6.28}, {"address": "icZAv4XySoSbxHrRDezBQwn8QwZPSecypUpBK53pump", "symbol": "Retail", "volume_h1": 11905.57, "price_change_h1": -5.2}]}, {"narrative": "animal-other", "strength": 0.856, "tokens": 24, "volume_h1": 437240.89999999997, "median_h1_pct": 0.0, "members": [{"address": "7PxNGKbpQ1WLzXc6cLq3drXa115rJPX7597cxw9kXqA1", "symbol": "blindape", "volume_h1": 185114.87, "price_change_h1": 83.03}, {"address": "AHbCwmjL7JvtXtMFzkoLhbyYxPPVvH7y1Jkkby3ktasZ", "symbol": "blindape", "volume_h1": 135004.81, "price_change_h1": 99.77}, {"address": "WJhYydA95C3ch9bEegyTBaUHpxTHkDy1QyQNEHFpump", "symbol": "blindape", "volume_h1": 60433.57, "price_change_h1": 165.0}, {"address": "G7vQWurMkMMm2dU3iZpXYFTHT9Biio4F4gZCrwFpKNwG", "symbol": "BIRB", "volume_h1": 26041.01, "price_change_h1": -1.6}, {"address": "4QbVqJJdGFftYoeEMjXLEpfBh3ncrQ6vLHx4yyF6D3eT", "symbol": "blindape", "volume_h1": 16984.23, "price_change_h1": 26.36}, {"address": "22wVHE4q9n3ZURzWT3F41D34Kqp9SsHCXPdmiPwgpump", "symbol": "CBSMOONER", "volume_h1": 4116.07, "price_change_h1": -95.47}, {"address": "AwZ5tmmBb4zjbL8ivPSxQzMWAWVjBg4RTWprFAXwpump", "symbol": "$SMOOSE", "volume_h1": 3562.84, "price_change_h1": 135.0}, {"address": "H1adbGC578HdoddVNAZT1Bn4uNrPiioTCfYmRjBHpump", "symbol": "Himgajria", "volume_h1": 2692.94, "price_change_h1": -20.47}, {"address": "E1jBbtQKKJ5HCvB78VEgEm5iAz6Rn5B8ps75KSiTLT9P", "symbol": "Hussein", "volume_h1": 1295.93, "price_change_h1": -30.47}, {"address": "83hjRA88wmusNgXtGQToTQSHoXeu5s3e1HGZbgBFpump", "symbol": "MOOZILLA", "volume_h1": 445.09, "price_change_h1": -3.21}, {"address": "2Yw1fxYEkV2PnNCwQ9qgX2d5ya8buKiNQKciTCx2Y5Ka", "symbol": "blindape", "volume_h1": 435.26, "price_change_h1": 8.91}, {"address": "2SNSDxEoC4snmSUYi7S5rsqFBvvzCqm7i93uBg7Mfray", "symbol": "CUPY", "volume_h1": 303.19, "price_change_h1": 0.09}, {"address": "HTFDa1F3YkA42NSKCZKJt5C3jCoqpktLtYAqcVRDpump", "symbol": "$MOONRAT", "volume_h1": 300.74, "price_change_h1": 2.58}, {"address": "6ov542fejCkVNWCeboHsT8NXZoocgyw4hyfV14yopump", "symbol": "NOPE", "volume_h1": 202.44, "price_change_h1": -33.38}, {"address": "8NdF45tRLstQBsH3wpeENJsWV2hi6TMqajWzAq3wpump", "symbol": "MOOZILLA", "volume_h1": 93.05, "price_change_h1": 4.77}]}, {"narrative": "~crypto", "strength": 0.836, "tokens": 13, "volume_h1": 948922.75, "median_h1_pct": 10.3, "members": [{"address": "5Lvs7V6AJhUgyAW5LTJVz46Z23kUqMaTMpWDCD1NEZHC", "symbol": "PUDGY", "volume_h1": 220631.35, "price_change_h1": 139.0}, {"address": "21qCC71G59QASc7aTU7GYFhy7WifpmP8PX9tDhWosHZz", "symbol": "PUDGY", "volume_h1": 218052.5, "price_change_h1": 106.0}, {"address": "ANhYwVbHvsxpLFZSYujvz9jEyFoNWqmMpAT4oUEC6ith", "symbol": "PUDGY", "volume_h1": 180290.36, "price_change_h1": 365.0}, {"address": "8ApVxHBVrGxMPU1ANbBNnWTBxKuFfX7qHhogzBuAEoq6", "symbol": "PUDGY", "volume_h1": 144215.65, "price_change_h1": 327.0}, {"address": "2Sbf5rRkS9Sam3Ro3HopXVKU9Um2rhi3BdnubZ6b369F", "symbol": "PUDGY", "volume_h1": 142772.68, "price_change_h1": 48.32}, {"address": "3QajTDQ3ophfJepAhM7A2QddvRPc12kjkr7Nh2QwKzvB", "symbol": "PUDGY", "volume_h1": 41155.49, "price_change_h1": 47.28}, {"address": "5KsDNm6a8uTTw3WjBaoMtNW6ZykHL9dSSC5xqo2uhVcu", "symbol": "PUDGY", "volume_h1": 549.39, "price_change_h1": -100.0}, {"address": "EPpGhuqwMPMCjMvae3kfFuw191ocJdiUStxC1vYypump", "symbol": "Crypt", "volume_h1": 519.68, "price_change_h1": -0.77}, {"address": "AWUePca4uCQJDoTKYtXnJz5FESyfsaFsvnYj8GBTpump", "symbol": "streets", "volume_h1": 288.46, "price_change_h1": 10.3}, {"address": "9QSFenbcR3T8wLVDCne3Mkz2Lk3T3xohNn5VAeQYpump", "symbol": "ACT:C", "volume_h1": 150.35, "price_change_h1": -6.32}, {"address": "EJUK5U5vyug99p64YxxLQSP51K5bWuBXG8hqzVNKUmpg", "symbol": "CRYPTOZOOLOGY", "volume_h1": 148.5, "price_change_h1": -6.25}, {"address": "7gdcURBxWCWptFPzwpM6n4yx982RqP46VAsQuubDH5u8", "symbol": "CSI6900", "volume_h1": 148.34, "price_change_h1": -6.27}, {"address": "EeBtzfdUJjiPKKxnVbGEiownCnu9H9QcfqfcME2Qpump", "symbol": "CODEWORDC", "volume_h1": 0.0, "price_change_h1": 0.0}]}], "rejects": [{"snapshot": {"address": "EPEqNdrnGSwVF5uaS8f6AoWDBxFE9mcAaazCDfy5nttq", "symbol": "BIGBUL", "name": "BIG BUL", "chain": "solana", "pair_address": "2dkggvsncx91v5fvfdgzgqR5kRkV2MteJSFNptjWRjbA", "dex": "meteora", "price_usd": 1.51e-05, "price_native": 2.017e-07, "liquidity_usd": 30.95, "fdv_usd": 15105.0, "market_cap_usd": 15105.0, "volume_h1": 246273.68, "volume_h24": 246273.68, "price_change_m5": -4.88, "price_change_h1": 114.0, "price_change_h6": 114.0, "price_change_h24": 114.0, "buys_h1": 2622, "sells_h1": 1305, "buys_m5": 165, "sells_m5": 158, "pair_created_at": 1784255216.0, "fetched_at": 1784256245.2087412}, "reason": "liquidity 31 < 25,000"}, {"snapshot": {"address": "CARDSccUMFKoPRZxt5vt3ksUbxEFEcnZ3H2pd3dKxYjp", "symbol": "CARDS", "name": "Collector Crypt", "chain": "solana", "pair_address": "HnhpJPJgBG2KwniMTNW8cVBHvk1hFog3RC3kjnyc23tD", "dex": "raydium", "price_usd": 0.1459, "price_native": 0.1459, "liquidity_usd": 2484226.54, "fdv_usd": 291829544.0, "market_cap_usd": 57365737.0, "volume_h1": 226328.64, "volume_h24": 1419896.28, "price_change_m5": 0.03, "price_change_h1": 5.25, "price_change_h6": -5.73, "price_change_h24": -4.39, "buys_h1": 169, "sells_h1": 221, "buys_m5": 1, "sells_m5": 2, "pair_created_at": 1756493686.0, "fetched_at": 1784256241.868427}, "reason": "liquidity too high (not early)"}, {"snapshot": {"address": "9cRCn9rGT8V2imeM2BaKs13yhMEais3ruM3rPvTGpump", "symbol": "ANSEM", "name": "The Black Bull", "chain": "solana", "pair_address": "FnzKY6x7entQ1eR3D225dQyT7ybfka4PskBMQhb8L3CC", "dex": "pumpswap", "price_usd": 0.1624, "price_native": 0.002169, "liquidity_usd": 1810142.24, "fdv_usd": 162428350.0, "market_cap_usd": 162428350.0, "volume_h1": 224541.28, "volume_h24": 13584821.11, "price_change_m5": -5.0, "price_change_h1": -3.14, "price_change_h6": -20.17, "price_change_h24": -7.43, "buys_h1": 586, "sells_h1": 542, "buys_m5": 171, "sells_m5": 55, "pair_created_at": 1781643948.0, "fetched_at": 1784256245.715266}, "reason": "mcap 162,428,350 out of range"}, {"snapshot": {"address": "D6ytjMdBBPoV8nsRHJhvrkpwF7sgVBYd7PufkRHNpump", "symbol": "CASHCOW", "name": "Cash Cow", "chain": "solana", "pair_address": "DCZLnE5pnSiLipEtgcLuLJZaHnRxjiqygkb4JBYTDiPq", "dex": "pumpswap", "price_usd": 0.000615, "price_native": 0.000615, "liquidity_usd": 85326.35, "fdv_usd": 615052.0, "market_cap_usd": 615052.0, "volume_h1": 223699.17, "volume_h24": 2842533.43, "price_change_m5": -0.92, "price_change_h1": -5.38, "price_change_h6": 4.57, "price_change_h24": 946.0, "buys_h1": 1799, "sells_h1": 1309, "buys_m5": 178, "sells_m5": 133, "pair_created_at": 1784179870.0, "fetched_at": 1784256240.59701}, "reason": "already pumped 946% in 24h"}, {"snapshot": {"address": "GjvVu8U71zWptAxG8PgyYFk1Cy9y3k3qXs96tzmh8op9", "symbol": "AAIF", "name": "American AI Fund", "chain": "solana", "pair_address": "DiwzGYmheuyDXzUDqaehCXW6r8rk3PhzbEroMQc1c3J6", "dex": "pumpswap", "price_usd": 0.004469, "price_native": 5.966e-05, "liquidity_usd": 22178.04, "fdv_usd": 4469353.0, "market_cap_usd": 4469353.0, "volume_h1": 207883.4, "volume_h24": 207883.4, "price_change_m5": 3.62, "price_change_h1": 59249.0, "price_change_h6": 59249.0, "price_change_h24": 59249.0, "buys_h1": 1058, "sells_h1": 458, "buys_m5": 345, "sells_m5": 144, "pair_created_at": 1784255274.0, "fetched_at": 1784256244.807621}, "reason": "liquidity 22,178 < 25,000"}, {"snapshot": {"address": "E7vTVLLaxV3y68cpnDx2Q7ExeznhWgJKwPziKDsrpump", "symbol": "HOMIE", "name": "Welcome Back Homie", "chain": "solana", "pair_address": "5fg5azit5ed8PaZ12vdtTTMGXw5moNsutYXJWA2w6qDY", "dex": "pumpswap", "price_usd": 0.0005194, "price_native": 6.937e-06, "liquidity_usd": 60844.03, "fdv_usd": 519456.0, "market_cap_usd": 519456.0, "volume_h1": 193765.11, "volume_h24": 4312568.21, "price_change_m5": -20.05, "price_change_h1": -14.89, "price_change_h6": 5.71, "price_change_h24": 1408.0, "buys_h1": 1171, "sells_h1": 1696, "buys_m5": 140, "sells_m5": 181, "pair_created_at": 1784179220.0, "fetched_at": 1784256245.715332}, "reason": "already pumped 1408% in 24h"}, {"snapshot": {"address": "9PZuQSM22CgtHdaf2tMRRLSH3Mh2nUCZpZqoTWf4QiHa", "symbol": "ACT:S", "name": "Act S: SAVE America Act", "chain": "solana", "pair_address": "D8NDuGCQx8TY51bh3UGPykkMFpb17UnSBik7uBSZ6kNb", "dex": "meteora", "price_usd": 4.742e-05, "price_native": 6.34e-07, "liquidity_usd": 15527.52, "fdv_usd": 47430.0, "market_cap_usd": 47430.0, "volume_h1": 192323.23, "volume_h24": 192323.23, "price_change_m5": 6.16, "price_change_h1": 626.0, "price_change_h6": 626.0, "price_change_h24": 626.0, "buys_h1": 1322, "sells_h1": 331, "buys_m5": 537, "sells_m5": 131, "pair_created_at": 1784255519.0, "fetched_at": 1784256243.093796}, "reason": "liquidity 15,528 < 25,000"}, {"snapshot": {"address": "7PxNGKbpQ1WLzXc6cLq3drXa115rJPX7597cxw9kXqA1", "symbol": "blindape", "name": "a blind ape", "chain": "solana", "pair_address": "2Bz8MR4iyrbxB57tjYkFKRkdP926YhiehdiCN1nDU4vp", "dex": "meteora", "price_usd": 1.375e-05, "price_native": 1.838e-07, "liquidity_usd": 20283.69, "fdv_usd": 13751.0, "market_cap_usd": 13751.0, "volume_h1": 185114.87, "volume_h24": 185114.87, "price_change_m5": 13.35, "price_change_h1": 83.03, "price_change_h6": 83.03, "price_change_h24": 83.03, "buys_h1": 2419, "sells_h1": 1125, "buys_m5": 489, "sells_m5": 466, "pair_created_at": 1784255537.0, "fetched_at": 1784256243.0936441}, "reason": "liquidity 20,284 < 25,000"}, {"snapshot": {"address": "B9x5VFGr3RJhHpzZKyXRvzAwk8Yhr8B4sfYJWCDDFZZd", "symbol": "\ud83e\ude96", "name": "\ud83e\ude96", "chain": "solana", "pair_address": "9NV9prc16BAauD7GTNuVb68h9mva3i4egaKT7zfFQbZ5", "dex": "meteora", "price_usd": 3.3e-05, "price_native": 4.413e-07, "liquidity_usd": 21081.91, "fdv_usd": 33010.0, "market_cap_usd": 33010.0, "volume_h1": 184455.76, "volume_h24": 184455.76, "price_change_m5": 8.9, "price_change_h1": 318.0, "price_change_h6": 318.0, "price_change_h24": 318.0, "buys_h1": 2389, "sells_h1": 1097, "buys_m5": 483, "sells_m5": 464, "pair_created_at": 1784255553.0, "fetched_at": 1784256243.093489}, "reason": "liquidity 21,082 < 25,000"}, {"snapshot": {"address": "Ge87EtsjwRQbHaqQmKRno69RFTwh9bfSsm99XNxTpump", "symbol": "Jimothy", "name": "Jimothy The Raccoon", "chain": "solana", "pair_address": "5PGhKctym6odbHGo2tKMST2AjmJsb2uZBQrKkn4ZuFT5", "dex": "pumpswap", "price_usd": 0.0003513, "price_native": 4.694e-06, "liquidity_usd": 47054.05, "fdv_usd": 351339.0, "market_cap_usd": 351339.0, "volume_h1": 161458.11, "volume_h24": 1168033.34, "price_change_m5": 2.12, "price_change_h1": 110.0, "price_change_h6": 116.0, "price_change_h24": 1023.0, "buys_h1": 1017, "sells_h1": 826, "buys_m5": 60, "sells_m5": 43, "pair_created_at": 1784196945.0, "fetched_at": 1784256245.7154298}, "reason": "already pumped 1023% in 24h"}, {"snapshot": {"address": "48bRSQqHphm8iSfWFCDG8XN2cg6ak11TLnadU1PETLc1", "symbol": "BLACKBULL", "name": "The Black Bull", "chain": "solana", "pair_address": "6kchNn3D7HDvKv6cLVanvA1Lz1N64qRrx1vhJ3eQc5BB", "dex": "meteora", "price_usd": 4.291e-05, "price_native": 5.737e-07, "liquidity_usd": 26575.74, "fdv_usd": 42918.0, "market_cap_usd": 42918.0, "volume_h1": 161299.06, "volume_h24": 161299.06, "price_change_m5": 3.22, "price_change_h1": 330.0, "price_change_h6": 330.0, "price_change_h24": 330.0, "buys_h1": 2463, "sells_h1": 1538, "buys_m5": 484, "sells_m5": 485, "pair_created_at": 1784255300.0, "fetched_at": 1784256244.807198}, "reason": "mcap 42,918 out of range"}, {"snapshot": {"address": "J968L8NU6vHjXeGSWMV9QKRARzQhGBa3Fm7QdEa2QJqk", "symbol": "CASHCOW", "name": "Cash Cow", "chain": "solana", "pair_address": "BLGEiycScTZBzPV9FGGYZBftEXraDoXt4Auv9JBBWM15", "dex": "meteora", "price_usd": 2.988e-05, "price_native": 3.994e-07, "liquidity_usd": 18670.52, "fdv_usd": 0.0, "market_cap_usd": 0.0, "volume_h1": 148426.29, "volume_h24": 148426.29, "price_change_m5": 2.36, "price_change_h1": 307.0, "price_change_h6": 307.0, "price_change_h24": 307.0, "buys_h1": 685, "sells_h1": 243, "buys_m5": 594, "sells_m5": 229, "pair_created_at": 1784255912.0, "fetched_at": 1784256240.596967}, "reason": "liquidity 18,671 < 25,000"}, {"snapshot": {"address": "rKvpqG7SBiT6HharwKZ4Fa2NXcrRxT4Sc9PaH6xq6qk", "symbol": "MORT", "name": "Mort Digsley", "chain": "solana", "pair_address": "3PDmbREKUyZjPaePG2SP6zWcpCLiBnu21w4E5ZqNM4tj", "dex": "meteora", "price_usd": 3.309e-05, "price_native": 4.424e-07, "liquidity_usd": 63407.7, "fdv_usd": 33097.0, "market_cap_usd": 33097.0, "volume_h1": 139898.84, "volume_h24": 139898.84, "price_change_m5": 1.01, "price_change_h1": 8.66, "price_change_h6": 8.66, "price_change_h24": 8.66, "buys_h1": 1933, "sells_h1": 918, "buys_m5": 548, "sells_m5": 520, "pair_created_at": 1784255718.0, "fetched_at": 1784256241.8687942}, "reason": "mcap 33,097 out of range"}, {"snapshot": {"address": "pumpCmXqMfrsAkQ5r49WcJnRayYRqmXz6ae8H7H9Dfn", "symbol": "PUMP", "name": "Pump", "chain": "solana", "pair_address": "2uF4Xh61rDwxnG9woyxsVQP7zuA6kLFpb3NvnRQeoiSd", "dex": "pumpswap", "price_usd": 0.00162, "price_native": 0.00162, "liquidity_usd": 13308447.9, "fdv_usd": 1375495494.0, "market_cap_usd": 1375495494.0, "volume_h1": 130553.47, "volume_h24": 2563344.52, "price_change_m5": -0.31, "price_change_h1": -2.11, "price_change_h6": -7.12, "price_change_h24": -2.81, "buys_h1": 69, "sells_h1": 211, "buys_m5": 0, "sells_m5": 33, "pair_created_at": 1752512149.0, "fetched_at": 1784256242.259729}, "reason": "liquidity too high (not early)"}, {"snapshot": {"address": "wZEG8xmEykSwi2vXsD86XYGdb2Q5y3fHpTQ24YZwr7Q", "symbol": "ROTATOOOOR", "name": "THE ROTATOOOOR", "chain": "solana", "pair_address": "6mkAJmBtHrWpoFXfr56FCQvzQGQWspKDqPwZoVony7z7", "dex": "meteora", "price_usd": 1.476e-05, "price_native": 1.973e-07, "liquidity_usd": 24053.45, "fdv_usd": 14760.0, "market_cap_usd": 14760.0, "volume_h1": 122769.22, "volume_h24": 122769.22, "price_change_m5": 8.08, "price_change_h1": 50.14, "price_change_h6": 50.14, "price_change_h24": 50.14, "buys_h1": 1986, "sells_h1": 743, "buys_m5": 532, "sells_m5": 515, "pair_created_at": 1784255803.0, "fetched_at": 1784256241.391742}, "reason": "liquidity 24,053 < 25,000"}, {"snapshot": {"address": "F4GpAFr6vrxU3Y887F3XWkXRgybCVjZNk63m72f6pump", "symbol": "TrumpCoin", "name": "Trump Coin", "chain": "solana", "pair_address": "FpJFWZ3nGFVYWkpDXZQM8QaLJzmy6U3NgaA8nc7SNDag", "dex": "pumpswap", "price_usd": 0.0004594, "price_native": 0.0004594, "liquidity_usd": 94512.49, "fdv_usd": 459441.0, "market_cap_usd": 459441.0, "volume_h1": 115571.05, "volume_h24": 1726504.69, "price_change_m5": 0.24, "price_change_h1": -0.54, "price_change_h6": -30.76, "price_change_h24": -46.39, "buys_h1": 747, "sells_h1": 497, "buys_m5": 27, "sells_m5": 29, "pair_created_at": 1784006805.0, "fetched_at": 1784256240.5970392}, "reason": "safety: LP locked only 0%"}, {"snapshot": {"address": "AUnKWxtBxX1B4s8ecxiiPjnAgFqKa6fs2Hh7hxmpump", "symbol": "GOATBATH", "name": "GOAT Bath", "chain": "solana", "pair_address": "2ZTAZtER8vd7r1nMnTm9ZpAdGrFVRcnCzYSfgtW6w4CT", "dex": "pumpswap", "price_usd": 6.838e-05, "price_native": 9.128e-07, "liquidity_usd": 19193.54, "fdv_usd": 68390.0, "market_cap_usd": 68390.0, "volume_h1": 113463.24, "volume_h24": 113463.24, "price_change_m5": 16.9, "price_change_h1": 40.19, "price_change_h6": 40.19, "price_change_h24": 40.19, "buys_h1": 1382, "sells_h1": 937, "buys_m5": 261, "sells_m5": 196, "pair_created_at": 1784255123.0, "fetched_at": 1784256239.2966568}, "reason": "liquidity 19,194 < 25,000"}, {"snapshot": {"address": "2agcQWJftYzYWJNDW4BPok1RKL1xVqpDJtT4SSVVpump", "symbol": "CS", "name": "ChainStudio", "chain": "solana", "pair_address": "D3vvifgjPi8AhAiEgrkxA1fYvHLvr8aW43cTZxGJ4BPZ", "dex": "pumpswap", "price_usd": 0.0004029, "price_native": 5.384e-06, "liquidity_usd": 47913.25, "fdv_usd": 402985.0, "market_cap_usd": 402985.0, "volume_h1": 107417.72, "volume_h24": 769701.32, "price_change_m5": -1.87, "price_change_h1": -12.34, "price_change_h6": 92.19, "price_change_h24": 862.0, "buys_h1": 630, "sells_h1": 691, "buys_m5": 14, "sells_m5": 22, "pair_created_at": 1784234616.0, "fetched_at": 1784256241.005974}, "reason": "already pumped 862% in 24h"}, {"snapshot": {"address": "AWJkSP77HTYnWyWiBfRoK5nurwP4ApVw1YeEugmepump", "symbol": "CASHGOAT", "name": "Cash Goat", "chain": "solana", "pair_address": "B2RGFp2RTcobX5witgdGFUby1xeVpwmXQpXqmawqRru8", "dex": "pumpswap", "price_usd": 0.0002615, "price_native": 3.49e-06, "liquidity_usd": 41545.83, "fdv_usd": 261523.0, "market_cap_usd": 261523.0, "volume_h1": 106986.84, "volume_h24": 1579467.54, "price_change_m5": 16.62, "price_change_h1": 115.0, "price_change_h6": 147.0, "price_change_h24": 597.0, "buys_h1": 1028, "sells_h1": 818, "buys_m5": 75, "sells_m5": 67, "pair_created_at": 1784172741.0, "fetched_at": 1784256241.0060291}, "reason": "already pumped 597% in 24h"}, {"snapshot": {"address": "AnKC4uw73qyDp4ot4pFsCeYNR5iEUUowooz6iZEj62wp", "symbol": "\ud83e\ude96", "name": "\ud83e\ude96", "chain": "solana", "pair_address": "3fuqGftBuoqjcZ2gyhV696kJw44ukHxvn1kg6xPhgGjV", "dex": "meteora", "price_usd": 1.244e-05, "price_native": 1.662e-07, "liquidity_usd": 11.1, "fdv_usd": 12446.0, "market_cap_usd": 12446.0, "volume_h1": 96317.67, "volume_h24": 96317.67, "price_change_m5": 3.42, "price_change_h1": 67.57, "price_change_h6": 67.57, "price_change_h24": 67.57, "buys_h1": 1798, "sells_h1": 561, "buys_m5": 222, "sells_m5": 214, "pair_created_at": 1784255718.0, "fetched_at": 1784256241.868814}, "reason": "liquidity 11 < 25,000"}, {"snapshot": {"address": "GZmN61QCYt5dsyHwTuuiRejUjgWNb2YcK8MPs8Ng6G4x", "symbol": "LIFE", "name": "one life, its worth an attempt", "chain": "solana", "pair_address": "7fhiAMXjmCTDe6uoXENYQErcnXPJ1vt6qkW7SLvmtSbD", "dex": "meteora", "price_usd": 1.47e-05, "price_native": 1.965e-07, "liquidity_usd": 23728.86, "fdv_usd": 0.0, "market_cap_usd": 0.0, "volume_h1": 90583.92, "volume_h24": 90583.92, "price_change_m5": 22.14, "price_change_h1": 53.12, "price_change_h6": 53.12, "price_change_h24": 53.12, "buys_h1": 1809, "sells_h1": 558, "buys_m5": 994, "sells_m5": 452, "pair_created_at": 1784255867.0, "fetched_at": 1784256240.597198}, "reason": "liquidity 23,729 < 25,000"}, {"snapshot": {"address": "CDyUSk43b19btJcf4fGNPQT2Rh8sARt4wERQq3PCpump", "symbol": "\ud83e\ude96", "name": "\ud83e\ude96", "chain": "solana", "pair_address": "3NVCWZHbWHg8HZ2RXFBN4K7UAb5uxbQkZU1ZjAamzmyn", "dex": "pumpfun", "price_usd": 2.701e-06, "price_native": 3.605e-08, "liquidity_usd": 0.0, "fdv_usd": 2701.3, "market_cap_usd": 2701.3, "volume_h1": 86419.34, "volume_h24": 86419.34, "price_change_m5": -45.15, "price_change_h1": -12.25, "price_change_h6": -12.25, "price_change_h24": -12.25, "buys_h1": 1517, "sells_h1": 1248, "buys_m5": 48, "sells_m5": 94, "pair_created_at": 1784254518.0, "fetched_at": 1784256242.697532}, "reason": "liquidity 0 < 25,000"}, {"snapshot": {"address": "B4ptaVsUe6YbtBwAS38WFeweSrVNfQLCcj9JRrtjU8vn", "symbol": "SOLdiers", "name": "SOLdiers", "chain": "solana", "pair_address": "B4JM2z5DAqNCJtSFm4F8v5pc88KA8Fk3oyCSwEfsq9bR", "dex": "pumpswap", "price_usd": 0.0006873, "price_native": 9.179e-06, "liquidity_usd": 94840.73, "fdv_usd": 687293.0, "market_cap_usd": 687293.0, "volume_h1": 84742.51, "volume_h24": 3255452.82, "price_change_m5": -1.61, "price_change_h1": -15.86, "price_change_h6": -26.44, "price_change_h24": -37.79, "buys_h1": 604, "sells_h1": 485, "buys_m5": 21, "sells_m5": 20, "pair_created_at": 1784122840.0, "fetched_at": 1784256245.715304}, "reason": "dumping (h1)"}, {"snapshot": {"address": "6yfHAwJ6oHB7J3jYyxEQri9w8fGY82WUV4HLVRiLqJRm", "symbol": "\ud83e\ude96", "name": "\ud83e\ude96", "chain": "solana", "pair_address": "9dkSeGjhDbYhPeFtEt4q6izLpBB8n94C4EC743fiWkmo", "dex": "meteora", "price_usd": 1.735e-05, "price_native": 2.319e-07, "liquidity_usd": 22898.17, "fdv_usd": 17350.0, "market_cap_usd": 17350.0, "volume_h1": 80972.79, "volume_h24": 80972.79, "price_change_m5": 22.87, "price_change_h1": 120.0, "price_change_h6": 120.0, "price_change_h24": 120.0, "buys_h1": 2096, "sells_h1": 682, "buys_m5": 388, "sells_m5": 402, "pair_created_at": 1784255708.0, "fetched_at": 1784256242.259443}, "reason": "liquidity 22,898 < 25,000"}, {"snapshot": {"address": "2SPQDWYw34FxvfpuA522g46ozZhwpbto5nyGU4u5pump", "symbol": "Toly", "name": "The Solana Clown", "chain": "solana", "pair_address": "2cQxf8NyS7r83no9EvwYCaAnCmgaMNSVUVmaxuSywNh5", "dex": "pumpfun", "price_usd": 1.655e-05, "price_native": 2.211e-07, "liquidity_usd": 0.0, "fdv_usd": 16558.0, "market_cap_usd": 16558.0, "volume_h1": 74379.46, "volume_h24": 74379.46, "price_change_m5": -34.42, "price_change_h1": 541.0, "price_change_h6": 541.0, "price_change_h24": 541.0, "buys_h1": 1741, "sells_h1": 1080, "buys_m5": 1278, "sells_m5": 752, "pair_created_at": 1784255795.0, "fetched_at": 1784256241.391774}, "reason": "liquidity 0 < 25,000"}], "mode": "paper", "profile": "aggressive", "status": {"equity": 1000.0, "cash": 1000.0, "starting_cash": 1000.0, "wins": 0, "losses": 0, "fees": 0.0, "killed": false, "halted_for_day": false}, "positions": [], "dd_reports": {"EKpQGSJtjMFqKZ9KQanSqYXRcF8fBopzLHYxdM65zcjm": "$WIF_EKpQGSJt.md", "TGTrnjkirTrmJwdrHZ9MRh4J46C8jFRMs3Ayyozpump": "smolcat_TGTrnjki.md", "5eAF5tC2BgjH9HF8XLKWjazgQU4KEL3ZqZXwRMSHpump": "CryingCat_5eAF5tC2.md", "DwA8xDTFt4aLujsHhW72LDYN5xsnFYsXLXVn1Guppump": "cat_DwA8xDTF.md", "9jTr8PmNX7eH9eK6aMG2MuYBzPZm16U7xhtHeaozBUwE": "$ACCOUNT_9jTr8PmN.md", "6JmbvqA1zY8T1H6qEMqzrjwSBTq2Ba1kqkywcUHw135n": "ACCOUNT_6JmbvqA1.md", "5rnhCX1oqY4wDEJcsrgpjvzTE2a39hpLaqSgZkou2t1r": "ACCOUNT_5rnhCX1o.md", "2x2yf9NMapNFuBYgfpBi9rFv1vLdu34DvwcRxEyuTGKc": "ACCOUNT_2x2yf9NM.md", "Dh6h5yk7qSBeZkbucNvXMcLcNnMp1ssi6Hp5HxGZAKbD": "Incum_Dh6h5yk7.md", "DUdzLjTTNHx6yTrYzJorbvc3x5ascZKFwmifj16RGMtm": "Incum_DUdzLjTT.md", "Gg2xdFJc6j4pVavUSfwHKZ4RAbJpbMcGZMKwGUaBpBpR": "Incum_Gg2xdFJc.md", "47BBWaDy3ZatHghsBg7q7mnrtoLZGxRD3Umkjov8b4Qb": "PUMPVERSIT_47BBWaDy.md", "9aEn4rKoHLA3R4o58cPEVHGBWPJR6GjtrPv6D9vtNxQc": "Incum_9aEn4rKo.md", "2agcQWJftYzYWJNDW4BPok1RKL1xVqpDJtT4SSVVpump": "CS_2agcQWJf.md", "He6pECrSVi123qabQJRiGEonMbBZ7e8PZ9NmUxKqpump": "bet_He6pECrS.md", "HNg5PYJmtqcmzXrv6S9zP1CDKk5BgDuyFBxbvNApump": "ALCH_HNg5PYJm.md", "BBSEsu4v5wR9h2HsnxPbVJuCKsRe2Cx77c598dKbpump": "Bullish_BBSEsu4v.md", "DXS6UqB4xGJoy6VSQFJE54zGX16dfJH6uCvT7fB6EW29": "BullBit_DXS6UqB4.md", "DKmJw1U4R8xHoU7Qk1R2npfD3cdyfTXmH2jcgyi1pump": "BullBit_DKmJw1U4.md", "9cRCn9rGT8V2imeM2BaKs13yhMEais3ruM3rPvTGpump": "ANSEM_9cRCn9rG.md", "7V6Sk63y8Rr1MvcN5mYNp61wgFhy4EeQg5gUASk9pump": "HBULL_7V6Sk63y.md", "G9j8WWDeJXZdvwQgP82ooDuHmpc3Gy8NCSins71Lpump": "BULLCAT_G9j8WWDe.md", "5Lvs7V6AJhUgyAW5LTJVz46Z23kUqMaTMpWDCD1NEZHC": "PUDGY_5Lvs7V6A.md", "21qCC71G59QASc7aTU7GYFhy7WifpmP8PX9tDhWosHZz": "PUDGY_21qCC71G.md", "ANhYwVbHvsxpLFZSYujvz9jEyFoNWqmMpAT4oUEC6ith": "PUDGY_ANhYwVbH.md", "2E1bcZmYuNy7fbfwJzcJGT578PhBJaJNqQ7PwwX7ZAiZ": "CHYNA_2E1bcZmY.md", "DtAvZU6K4bitFevYXPxwD929myw2PbvJbJPeMJjnsQ7W": "CHYNA_DtAvZU6K.md", "8pStW6495TdRFHrf5Jc1cJgLLqYLMPJqXgXbmbbtB371": "CHYNA_8pStW649.md", "BQK9FSFEuj7ibuT6VLnZGUe5NWRDnKCwnqQvxBzCJs2K": "FORGE_BQK9FSFE.md", "FmVtrnVsMLgpZhxxoTmh7MH43mon4jzpU5G4HzSvHGcf": "FORGE_FmVtrnVs.md", "RPC8MbAndTBJ56nT25GkD7ZT38xsKjD6Ybo94HHJggF": "FORGE_RPC8MbAn.md"}}