{"ts": 1784280805.092503, "discovered": 461, "tradeable": 149, "prefiltered": 3, "channels": {"dexscreener_boosts": 19, "dexscreener_profiles": 15, "gecko_new_pools": 40, "gecko_trending": 20, "jupiter_recent": 30, "pumpfun_graduations": 7, "helius_new_pools": 79}, "watchlist": 458, "candidates": [], "narratives": [{"narrative": "~black", "strength": 0.9, "tokens": 13, "volume_h1": 2850515.89, "median_h1_pct": -6.3, "members": [{"address": "HBWfbvbRvFQuw3X1PpmVeBKNpm5eFyKpYpB6jUDSvRjT", "symbol": "$MENSAHOOD", "volume_h1": 2250134.66, "price_change_h1": 44.64}, {"address": "CZSJaDpGigeprcSvdmtq3ePQPo3ZNYJeNoEvMDxBpump", "symbol": "MENSAHOOD", "volume_h1": 539803.24, "price_change_h1": -98.36}, {"address": "CFPkPq1eYPR8GLzEo59wUbbMioX4bshaTQiSGzTSpump", "symbol": "MENSA", "volume_h1": 28108.55, "price_change_h1": 19.37}, {"address": "AgX2sWJHfbbegtpn5bwbU5QZ5ybVTotY2ZWwiutNpump", "symbol": "COCKSA", "volume_h1": 13671.5, "price_change_h1": -0.67}, {"address": "gCyGZU1eLHKoMh9Q3dsvXc5LwQCWHoTnY5HSqdupump", "symbol": "TBP", "volume_h1": 11269.26, "price_change_h1": 2.1}, {"address": "2ea1xeHequESTveTQecs8N5wjZZaV5suceEHo3rkpump", "symbol": "MENSASOL", "volume_h1": 5077.67, "price_change_h1": -0.65}, {"address": "HhjoehZszwZQ1YGnqVrtkg4yAgAFjii7RNh7EJuNpump", "symbol": "BC", "volume_h1": 1482.16, "price_change_h1": -99.92}, {"address": "Bx2FQdixmxxZDfJrKEHaqzDM9Cd3Rw45vWDZdfb5pump", "symbol": "BC", "volume_h1": 379.62, "price_change_h1": -99.86}, {"address": "HprmQGLA9T4dgcq3vNiUen2sjehjWi2h515broPepump", "symbol": "BC", "volume_h1": 162.33, "price_change_h1": -69.6}, {"address": "8U5TfoYeUNKxiJvcYXGMfWkyB9zP6A8JeViCQHA5pump", "symbol": "MENSAHOOD", "volume_h1": 156.23, "price_change_h1": -88.06}, {"address": "ErvwD3LPXG64cXTvTbpuVYDpS16usVAmGqGU71xgpump", "symbol": "MENSAHOOD", "volume_h1": 149.05, "price_change_h1": -6.33}, {"address": "A4uanUUzd6nStweuV7kiWNQadmEYh3NhM9PVgCBkpump", "symbol": "BC", "volume_h1": 114.18, "price_change_h1": -97.97}, {"address": "5rvBcDkqDi8Lg7JTDEKC6ak4L8TvL6nJLgKdm3Mipump", "symbol": "TBB", "volume_h1": 7.44, "price_change_h1": -0.24}]}, {"narrative": "cat", "strength": 0.883, "tokens": 54, "volume_h1": 476018.07, "median_h1_pct": -1.1, "members": [{"address": "2u6Dq88YjY2Ff1RexGN4dNp51T9bFvAYsY1CVYi8dUej", "symbol": "BLACKCAT", "volume_h1": 330164.61, "price_change_h1": 290.0}, {"address": "G9j8WWDeJXZdvwQgP82ooDuHmpc3Gy8NCSins71Lpump", "symbol": "BULLCAT", "volume_h1": 36978.66, "price_change_h1": -9.25}, {"address": "23s15mY3eqrCuiKXi2oWUKmk3aJFLBB5MHjEDyoipump", "symbol": "CRABCAT", "volume_h1": 29727.58, "price_change_h1": -98.32}, {"address": "GTG8JYafTa3DzzZUUN1RHNdyVDEzMDBuqDMq3aJvpump", "symbol": "SMIRKCAT", "volume_h1": 9936.94, "price_change_h1": 39.46}, {"address": "D18pKmoBA4U8NzuMgapjQHYKrJsMbdXbZv5NSr6Zpump", "symbol": "CARDCAT", "volume_h1": 8983.15, "price_change_h1": -52.91}, {"address": "EA7JYMHuKtT2FDzoFPVu3xtc1ZTeBy6eDie4gtGepump", "symbol": "CATO", "volume_h1": 7478.88, "price_change_h1": -16.93}, {"address": "CyJ6QEYK3cfJcqKKMZy7W8M2h95GErWBNyiwCqSSpump", "symbol": "CARDCAT", "volume_h1": 7408.04, "price_change_h1": 58.59}, {"address": "HpNXTwQsSH9tXM97o77qthW7ZqDfkX4DYZYMsLTkpump", "symbol": "CHILL", "volume_h1": 6786.82, "price_change_h1": -13.29}, {"address": "DYBSKK8yjC1EKBPW8kCHhtXRMjGVSpwStATDoYxepump", "symbol": "SMIRKCAT", "volume_h1": 5726.98, "price_change_h1": -3.23}, {"address": "BBq29YqimAwWa9mgFLrRv7gUieji1ZeYriLnZyMUB14z", "symbol": "MEOWLD", "volume_h1": 4087.63, "price_change_h1": -11.99}, {"address": "3Tf3RD5t45wQJF8uEYVXpR2M4wBiCaSNwUWENzVGpump", "symbol": "Meowpin", "volume_h1": 3949.64, "price_change_h1": -7.05}, {"address": "GziZGRmvh9DMfwtc3qfFScjCW7di5wuqFNbnSQ3Ppump", "symbol": "Solcat", "volume_h1": 3718.49, "price_change_h1": 30.56}, {"address": "7GCihgDB8fe6KNjn2MYtkzZcRjQy3t9GHdC8uHYmW2hr", "symbol": "POPCAT", "volume_h1": 3307.26, "price_change_h1": 0.94}, {"address": "4N4DnNo3qpPks9aQCkcWkzoir8tnvT6diS4TnnZibonk", "symbol": "KITTY", "volume_h1": 2765.7, "price_change_h1": 0.01}, {"address": "FGHVuffg46d7xo8SF4NFWuKRpK1tMQco2hopAWZ5pump", "symbol": "WC", "volume_h1": 2686.59, "price_change_h1": -12.06}]}, {"narrative": "~slopped", "strength": 0.834, "tokens": 8, "volume_h1": 546866.4299999999, "median_h1_pct": 10.1, "members": [{"address": "ABoLewVjfLwJU38pFvNgUfSZCBPDGEA1suGrhj5VGdQQ", "symbol": "Slopped", "volume_h1": 267575.66, "price_change_h1": 106.0}, {"address": "3DWGb5wsipHWxTHxS3weBX6sKZw9ivJka2HXSVszh4RR", "symbol": "Slopped", "volume_h1": 232790.53, "price_change_h1": 459.0}, {"address": "9j7w44zkaG3Z5xdUPJiepQCsrqnpqLW2UzjtmFrGpump", "symbol": "Slopped", "volume_h1": 43069.34, "price_change_h1": -0.14}, {"address": "3BycnBiWLoNLuomDbYRFjZWHkWRb1dtdRx21Q8cpW3Xi", "symbol": "Slopped", "volume_h1": 1922.8, "price_change_h1": 22.52}, {"address": "BX765L9BeiaoYPfaCyGd46HiRsDvg8LMCTU2ULNTURt5", "symbol": "Slopped", "volume_h1": 1028.25, "price_change_h1": 17.12}, {"address": "FrMWuMDzC1P781mnLUqw1ueB1kxdLzkAjKHPAkFdiFYN", "symbol": "Slopped", "volume_h1": 230.04, "price_change_h1": 3.06}, {"address": "F7X3qP2QtMv3kSNXzPEQDiGgyaxVpPJD34BNVAA565dA", "symbol": "Slopped", "volume_h1": 230.01, "price_change_h1": 3.04}, {"address": "FD3HzEq8aicctmPappdP5Bks1Qr6Y8uAY7ENaBBJpump", "symbol": "Slopped", "volume_h1": 19.8, "price_change_h1": 1.87}]}, {"narrative": "~cow", "strength": 0.772, "tokens": 3, "volume_h1": 999608.28, "median_h1_pct": 21.8, "members": [{"address": "12rupRSNZzDTXLzzKUuLcz4p7mSDky6ksC1aLxBBjxhG", "symbol": "CASHCOW", "volume_h1": 984326.9, "price_change_h1": 69.23}, {"address": "D6ytjMdBBPoV8nsRHJhvrkpwF7sgVBYd7PufkRHNpump", "symbol": "CASHCOW", "volume_h1": 15281.38, "price_change_h1": 21.79}, {"address": "5CfHGH7WZUaQ43XB5vbStZT61iiEKGfBrsSMqEBXLyWW", "symbol": "CASHCOW", "volume_h1": 0.0, "price_change_h1": 0.0}]}, {"narrative": "~san", "strength": 0.768, "tokens": 20, "volume_h1": 1277589.57, "median_h1_pct": 2.1, "members": [{"address": "3YiY5JMokTdP6Phk4mDsKyV5geV5ADCbETH6zHXQHs9d", "symbol": "5", "volume_h1": 412187.68, "price_change_h1": 145.0}, {"address": "BygNt6JxXKYm2czMroxQzPVA9oDeZgnivpTSWUhraK7i", "symbol": "5", "volume_h1": 302261.65, "price_change_h1": 106.0}, {"address": "J4idgExTUcrgJkrMazz1wU9PCRZhsoS2YkvKFGyfkCLe", "symbol": "5", "volume_h1": 180315.82, "price_change_h1": 7.23}, {"address": "6W1ycBgawCcRnjy2santpMBkQk9aHYvhvKLvgC5C63r9", "symbol": "5", "volume_h1": 104208.41, "price_change_h1": 10.75}, {"address": "cqcmYVJajiR8KVKG1kwg2j7BjxrDLuWP39yvSEGE2Pd", "symbol": "5", "volume_h1": 95877.86, "price_change_h1": 6.38}, {"address": "HsD4XWuvMghKmKG1znYieGpqPbUW67aPCrZxZh5wGaDc", "symbol": "5", "volume_h1": 58951.89, "price_change_h1": 61.16}, {"address": "7wfRDMV2ZrzQZky3eHfmiJrztaPt9ZpUDKYhu6dmoyYV", "symbol": "5", "volume_h1": 50714.75, "price_change_h1": 40.03}, {"address": "FbPCmf6bodgBL6jP9WaXVDbX9CSwEL6ZeY1aGeR7pump", "symbol": "5", "volume_h1": 45699.63, "price_change_h1": 93.51}, {"address": "89BmH4DSgB8Xh8VLiVya3RH83tS1KnWDVSwPQD3Zpump", "symbol": "\u30b4\u30b8\u30e9", "volume_h1": 19199.37, "price_change_h1": -19.64}, {"address": "BEsC5vcsDLin6x5ezc1Hn5qkQgSbu4Fu17XJg7wupump", "symbol": "5", "volume_h1": 3283.44, "price_change_h1": -11.55}, {"address": "BQkftEfPYrDy1RQX7mNGexFnavLxEQPvGkahxDUQpump", "symbol": "5", "volume_h1": 2448.02, "price_change_h1": -5.82}, {"address": "5J2hjUj2cChGNLsL6WsXYyMSfLUcW5ZKzY9QjF4epump", "symbol": "5", "volume_h1": 795.22, "price_change_h1": -6.31}, {"address": "817osfojWhWQ6wi3MHSLrGmUgYES79GUCttzqyLopump", "symbol": "\u30b4\u30b8\u30e9", "volume_h1": 513.22, "price_change_h1": -96.77}, {"address": "4PTrW3dv63NScx8HSx6mxG2EHDjUFeFwix1fBzgfLrvX", "symbol": "5", "volume_h1": 302.37, "price_change_h1": 4.3}, {"address": "4yjnoNLC2zFCvoiBKZNzVV6HCSA3Qw3qjA3X2mF4joRX", "symbol": "5", "volume_h1": 301.68, "price_change_h1": 4.3}]}, {"narrative": "ai", "strength": 0.75, "tokens": 42, "volume_h1": 815922.79, "median_h1_pct": -0.3, "members": [{"address": "BtsW2oWyBMSCwXmyTFafEkhc9xTtJBDphdQ2tMCvD3g7", "symbol": "URKL", "volume_h1": 471988.35, "price_change_h1": 771.0}, {"address": "itQeBVnCY9U2fUwrKSi7D2Xcq46ZMaKsPfacmxJpump", "symbol": "URKL ", "volume_h1": 74690.12, "price_change_h1": 44.28}, {"address": "He6pECrSVi123qabQJRiGEonMbBZ7e8PZ9NmUxKqpump", "symbol": "bet", "volume_h1": 37778.04, "price_change_h1": -18.54}, {"address": "DCAAhXhbHpThEWffDtHni99uhsJSM9oVjtrxHxj79D6w", "symbol": "URKL", "volume_h1": 37438.73, "price_change_h1": 20.07}, {"address": "2agcQWJftYzYWJNDW4BPok1RKL1xVqpDJtT4SSVVpump", "symbol": "CS", "volume_h1": 36605.55, "price_change_h1": 3.72}, {"address": "DL5rcwYY89NtBSyqLAoRgyXFzKbGwrifNxLXHiW4pump", "symbol": "ITSC", "volume_h1": 29610.33, "price_change_h1": 110.0}, {"address": "HgzfhN9hAg54x5wxHjhqtifxiZ4xRKAnukPEY5Zjpump", "symbol": "Daffal", "volume_h1": 29394.65, "price_change_h1": 101.0}, {"address": "HNg5PYJmtqcmzXrv6S9zP1CDKk5BgDuyFBxbvNApump", "symbol": "ALCH", "volume_h1": 26239.22, "price_change_h1": -0.68}, {"address": "Gz8GEGnbp8ER7JRHma3JopPxhgxXPcNHm6uiQ9WLpump", "symbol": "Runner", "volume_h1": 18336.86, "price_change_h1": -0.29}, {"address": "3v2ekTxcn6voD4RDzhwaf5z1VXFxGBxoUKEWZRfBpump", "symbol": "YUKI", "volume_h1": 10100.63, "price_change_h1": -10.15}, {"address": "61V8vBaqAGMpgDQi4JcAwo1dmBGHsyhzodcPqnEVpump", "symbol": "arc", "volume_h1": 8137.82, "price_change_h1": -0.38}, {"address": "TH3iLdwQvvhA8aKLwZD6FvLCKykWkriRTEboz4Fpump", "symbol": "E-pi", "volume_h1": 5815.56, "price_change_h1": -21.58}, {"address": "FX8SxSkcBjKKcdL6w3x3Z3D56PpXfh7B874WyjvGpump", "symbol": "Unbothered", "volume_h1": 5232.52, "price_change_h1": -17.39}, {"address": "DSkEf7JyZGYSPTyQjupGrKT1REKtoAdF4teYPxCipump", "symbol": "MNEMO", "volume_h1": 5059.48, "price_change_h1": -4.37}, {"address": "6NbGvNSEAY75NJGxDVzwSBeD7zyu4JfNmrNsBKFLpump", "symbol": "Yuki", "volume_h1": 4280.28, "price_change_h1": -3.53}]}, {"narrative": "~wang", "strength": 0.75, "tokens": 62, "volume_h1": 3157965.42, "median_h1_pct": 0.0, "members": [{"address": "496xCvJ4KGCzCRSSmYZ4H7stdkwEQUBEbBsHdnqKpd7F", "symbol": "\u65fa\u65fa", "volume_h1": 803261.08, "price_change_h1": 1370.0}, {"address": "Ezx6F3g2f92p86wv9vb5Tw6q8bFXFdtUQHDZs7qzWRYH", "symbol": "\u65fa\u65fa", "volume_h1": 372012.82, "price_change_h1": 6.96}, {"address": "TvfcLD4aPBD9MQ12me4DU89rdHTftMm3rXNTjfsR2nL", "symbol": "\u738b\u738b", "volume_h1": 278627.78, "price_change_h1": 2301.0}, {"address": "GQQmDfbwVhkcEyaLxaQeum74aQP1e3T9J97yzg9QwTFL", "symbol": "\u65fa\u65fa", "volume_h1": 244961.58, "price_change_h1": 562.0}, {"address": "HtuCPcNuuEMuoTSBAFfyFRvu3BzJ3kRgr5WiWQyZpump", "symbol": "WangWang", "volume_h1": 222891.94, "price_change_h1": -15.92}, {"address": "7z5KZpYj7BEnGKGCY3kDkaX32ueBSNp8QjvFq8Lxpump", "symbol": "\u65fa\u65fa", "volume_h1": 209853.9, "price_change_h1": 10.58}, {"address": "5hJUicZb1uZSwuYmsmo1uXZp41sJcNo7mvKjQDgbkADF", "symbol": "WangWang", "volume_h1": 166692.73, "price_change_h1": 577.0}, {"address": "EJRF8jUTY97DaTt5dyas28REfjQvPrxDaHNyHiQu9Vog", "symbol": "\u65fa\u65fa", "volume_h1": 134988.54, "price_change_h1": 523.0}, {"address": "8CJNy8NGRpGVMKw1SnHoZBU8tc7Tz6yNUb7Aa49ZaXH5", "symbol": "\u65fa\u65fa", "volume_h1": 133982.85, "price_change_h1": 677.0}, {"address": "9JtVEmpJhi1tXb5pGzi2ZCC9qHaxuVs3TiMKAT5ghNQc", "symbol": "WangWang", "volume_h1": 113967.83, "price_change_h1": 68.2}, {"address": "CsB957Ca4ZWVLBk7iHMfscmstK6cWuXrtxz82yZRWQ3U", "symbol": "WangWang", "volume_h1": 100551.07, "price_change_h1": 74.61}, {"address": "9i9azL4bDj6zHonYha8NBDFkVatPHVVCjQBBNzmyfgKq", "symbol": "\u65fa\u65fa", "volume_h1": 72752.76, "price_change_h1": 9.9}, {"address": "3xNq1qvbdz65vEEbXq8TkU7g7K82fpmjtui9DPEM7DNj", "symbol": "Wang Wang", "volume_h1": 59089.53, "price_change_h1": 76.42}, {"address": "EUu5YQRzjGAfoRX5dBAJ9i1NVdAcytJXVxNh65uYmdVA", "symbol": "WangWang", "volume_h1": 49281.92, "price_change_h1": 37.04}, {"address": "9aWL6FHeagdLQJrSUBteXP8fVi82xNX5LyxfwQTNU3Px", "symbol": "\u65fa\u65fa", "volume_h1": 42010.95, "price_change_h1": 438637.0}]}, {"narrative": "dog", "strength": 0.75, "tokens": 59, "volume_h1": 529761.18, "median_h1_pct": -0.0, "members": [{"address": "EcCjMAJEXcBMZ5QWtX4PKUkpSvoEFdcs41MKcXjwMEbu", "symbol": "Princess", "volume_h1": 325753.07, "price_change_h1": 146.0}, {"address": "7YCTXLpRn1zSgfU7o99RsyCnu7B8vUJAs9HxXKvMpump", "symbol": "Wifout", "volume_h1": 66861.39, "price_change_h1": 71.67}, {"address": "4RTfNQMYrmwgJusXW4YyVDtSi5BgCrr5E56SBrfeMMUb", "symbol": "Ivy", "volume_h1": 46041.8, "price_change_h1": 83.47}, {"address": "EKpQGSJtjMFqKZ9KQanSqYXRcF8fBopzLHYxdM65zcjm", "symbol": "$WIF", "volume_h1": 14912.81, "price_change_h1": 0.6}, {"address": "3abLc5ts3yEdAhcN6aHW4RYPepreE84ZHzt14axwpump", "symbol": "Princess", "volume_h1": 14509.1, "price_change_h1": -46.84}, {"address": "2GXS64a16q27aEzyucNgzFAe8FhRFBsqdHSb4aoxWrfN", "symbol": "drooling", "volume_h1": 12185.02, "price_change_h1": 21.65}, {"address": "DQSxjRkT9KLEkB7MsXou2ppW7pgNHoC6i5uviecDpump", "symbol": "NYPDR", "volume_h1": 11740.49, "price_change_h1": 57.34}, {"address": "7EPAM9FJkVFkuSxeRKjk8AHAbWWc5ya4g5EzcEkGqKED", "symbol": "EZPZ", "volume_h1": 6899.57, "price_change_h1": 21.23}, {"address": "6F3GfuhepbBZJ9qUquZgbddhTDKPkxCen4HvaBiapump", "symbol": "Elon", "volume_h1": 6627.99, "price_change_h1": -22.88}, {"address": "5rU554CbUhnbjYdZBnMupyuYfdkf2RuqcpEvPuGGpump", "symbol": "Ivy", "volume_h1": 4811.82, "price_change_h1": -10.85}, {"address": "GGH6dyjTufLvXtaVLWSPDCv8Rm6DQ9obipYnQHjppump", "symbol": "Ivy", "volume_h1": 3938.7, "price_change_h1": -16.87}, {"address": "HUdYPnE7t3guP7iW158zZMjo5D2jT6L7EPKdozW4pump", "symbol": "glow", "volume_h1": 3156.65, "price_change_h1": -7.89}, {"address": "CMKM4g8ruQzr6mG5eBSUgFpgoxDjbYi8W6JNP1beYizi", "symbol": "PONSDOG", "volume_h1": 2913.74, "price_change_h1": 46.53}, {"address": "ERn85GVTxo95Vk9tYbgyZn9kzHTJeLVjgfXZMEtxnmLR", "symbol": "Wifout", "volume_h1": 2721.36, "price_change_h1": -100.0}, {"address": "EC1fZBQuNa7jGDCE5LXtXvuvHxzfbJdhGzxXQTjMpump", "symbol": "WIF", "volume_h1": 1841.79, "price_change_h1": -26.5}]}], "rejects": [{"snapshot": {"address": "4AzQbJYUAqyQPPXMDvy7yZWTMErHYdmDFGMVYeqm2DCv", "symbol": "HOOD", "name": "Robinhood", "chain": "solana", "pair_address": "5cnvYu8JdMM43emRBtAqRpYWkMYBQ59MUKt8Bpdf2HPS", "dex": "pumpswap", "price_usd": 1.059e-05, "price_native": 1.418e-07, "liquidity_usd": 261344.49, "fdv_usd": 1059270.0, "market_cap_usd": 1059270.0, "volume_h1": 17913638.0, "volume_h24": 17913638.0, "price_change_m5": 1.25, "price_change_h1": 316.0, "price_change_h6": 316.0, "price_change_h24": 316.0, "buys_h1": 14038, "sells_h1": 11574, "buys_m5": 1574, "sells_m5": 1493, "pair_created_at": 1784278302.0, "fetched_at": 1784280765.764411}, "reason": "already pumped 316% in 24h"}, {"snapshot": {"address": "HBWfbvbRvFQuw3X1PpmVeBKNpm5eFyKpYpB6jUDSvRjT", "symbol": "$MENSAHOOD", "name": "The Black Robin", "chain": "solana", "pair_address": "Dgi5So8z8fbo5nAAiNowswcMrCmtyiiTeg5cgr19Qss4", "dex": "pumpswap", "price_usd": 5.406e-05, "price_native": 7.24e-07, "liquidity_usd": 95577.84, "fdv_usd": 54062.0, "market_cap_usd": 54062.0, "volume_h1": 2250134.66, "volume_h24": 2250134.66, "price_change_m5": 4.04, "price_change_h1": 44.64, "price_change_h6": 44.64, "price_change_h24": 44.64, "buys_h1": 2616, "sells_h1": 1657, "buys_m5": 392, "sells_m5": 247, "pair_created_at": 1784278931.0, "fetched_at": 1784280761.92816}, "reason": "mcap 54,062 out of range"}, {"snapshot": {"address": "12rupRSNZzDTXLzzKUuLcz4p7mSDky6ksC1aLxBBjxhG", "symbol": "CASHCOW", "name": "Cash Cow", "chain": "solana", "pair_address": "CP4R48onk8Gayoh4BFJdRtfaEEd9fkiHxxhXsDt6hAwC", "dex": "pumpswap", "price_usd": 7.598e-05, "price_native": 1.017e-06, "liquidity_usd": 119327.97, "fdv_usd": 75987.0, "market_cap_usd": 75987.0, "volume_h1": 984326.9, "volume_h24": 984326.9, "price_change_m5": 3.61, "price_change_h1": 69.23, "price_change_h6": 69.23, "price_change_h24": 69.23, "buys_h1": 1474, "sells_h1": 1130, "buys_m5": 632, "sells_m5": 499, "pair_created_at": 1784280048.0, "fetched_at": 1784280763.617578}, "reason": "mcap 75,987 out of range"}, {"snapshot": {"address": "CZSJaDpGigeprcSvdmtq3ePQPo3ZNYJeNoEvMDxBpump", "symbol": "MENSAHOOD", "name": "The Black Robin", "chain": "solana", "pair_address": "7bGeHGnpJUSDqcM461sz442NymEXDXcSrtj9dd6jRL9E", "dex": "pumpswap", "price_usd": 4.975e-06, "price_native": 6.659e-08, "liquidity_usd": 5323.72, "fdv_usd": 4976.0, "market_cap_usd": 4976.0, "volume_h1": 539803.24, "volume_h24": 729096.08, "price_change_m5": 10.19, "price_change_h1": -98.36, "price_change_h6": -83.84, "price_change_h24": -83.84, "buys_h1": 3103, "sells_h1": 2555, "buys_m5": 38, "sells_m5": 12, "pair_created_at": 1784274681.0, "fetched_at": 1784280760.717791}, "reason": "liquidity 5,324 < 25,000"}, {"snapshot": {"address": "ABoLewVjfLwJU38pFvNgUfSZCBPDGEA1suGrhj5VGdQQ", "symbol": "Slopped", "name": "Slopped", "chain": "solana", "pair_address": "DYww4g2cifWBY4vWGRTfKNBCtFsA8ZsBMHif6EdHKoW5", "dex": "meteora", "price_usd": 1.516e-05, "price_native": 2.029e-07, "liquidity_usd": 20752.65, "fdv_usd": 15168.0, "market_cap_usd": 15168.0, "volume_h1": 267575.66, "volume_h24": 267575.66, "price_change_m5": 18.6, "price_change_h1": 106.0, "price_change_h6": 106.0, "price_change_h24": 106.0, "buys_h1": 2865, "sells_h1": 1601, "buys_m5": 442, "sells_m5": 425, "pair_created_at": 1784279772.0, "fetched_at": 1784280764.894978}, "reason": "liquidity 20,753 < 25,000"}, {"snapshot": {"address": "2bDpYrcGmtgnJ3PtzfN6kmjyTbRk7bQrmyj3VD7ZMYoZ", "symbol": "4", "name": "The Patriotic 4", "chain": "solana", "pair_address": "J3cAWAwVtKrM2YFpn6kt9D5zeUCGArx7FRQEb9o8LRrX", "dex": "meteora", "price_usd": 1.836e-05, "price_native": 2.458e-07, "liquidity_usd": 26300.63, "fdv_usd": 18368.0, "market_cap_usd": 18368.0, "volume_h1": 262414.39, "volume_h24": 262414.39, "price_change_m5": 7.94, "price_change_h1": 88.71, "price_change_h6": 88.71, "price_change_h24": 88.71, "buys_h1": 2930, "sells_h1": 1647, "buys_m5": 491, "sells_m5": 470, "pair_created_at": 1784279835.0, "fetched_at": 1784280764.4031339}, "reason": "mcap 18,368 out of range"}, {"snapshot": {"address": "CP3k3NMUwMwEMiMtGueEPsSW8rGGbnSqKaTtYHLPFsr3", "symbol": "FRANCE", "name": "France", "chain": "solana", "pair_address": "EFK3jY8ApddV2b6XcssPa5nm3bs417tLpXpsTnusLnsu", "dex": "meteora", "price_usd": 8.512e-05, "price_native": 1.139e-06, "liquidity_usd": 20674.17, "fdv_usd": 85121.0, "market_cap_usd": 85121.0, "volume_h1": 253598.31, "volume_h24": 253598.31, "price_change_m5": 65.35, "price_change_h1": 1095.0, "price_change_h6": 1095.0, "price_change_h24": 1095.0, "buys_h1": 2599, "sells_h1": 805, "buys_m5": 223, "sells_m5": 250, "pair_created_at": 1784279886.0, "fetched_at": 1784280764.403104}, "reason": "liquidity 20,674 < 25,000"}, {"snapshot": {"address": "Ge87EtsjwRQbHaqQmKRno69RFTwh9bfSsm99XNxTpump", "symbol": "Jimothy", "name": "Jimothy The Raccoon", "chain": "solana", "pair_address": "5PGhKctym6odbHGo2tKMST2AjmJsb2uZBQrKkn4ZuFT5", "dex": "pumpswap", "price_usd": 0.001916, "price_native": 2.566e-05, "liquidity_usd": 114084.56, "fdv_usd": 1916495.0, "market_cap_usd": 1916495.0, "volume_h1": 249105.37, "volume_h24": 2752685.66, "price_change_m5": -1.32, "price_change_h1": 25.21, "price_change_h6": 339.0, "price_change_h24": 6023.0, "buys_h1": 1468, "sells_h1": 1394, "buys_m5": 66, "sells_m5": 88, "pair_created_at": 1784196945.0, "fetched_at": 1784280762.332576}, "reason": "liq/mcap 6.0% < 10%"}, {"snapshot": {"address": "GQQmDfbwVhkcEyaLxaQeum74aQP1e3T9J97yzg9QwTFL", "symbol": "\u65fa\u65fa", "name": "Justice for Wang Wang", "chain": "solana", "pair_address": "Gk1U8XmN6vSNfLfQX9rHhFaqFc1eQM7hnJYyeqwpQoeL", "dex": "meteora", "price_usd": 4.826e-05, "price_native": 6.459e-07, "liquidity_usd": 20411.55, "fdv_usd": 48265.0, "market_cap_usd": 48265.0, "volume_h1": 244961.58, "volume_h24": 244961.58, "price_change_m5": 40.88, "price_change_h1": 562.0, "price_change_h6": 562.0, "price_change_h24": 562.0, "buys_h1": 557, "sells_h1": 511, "buys_m5": 154, "sells_m5": 134, "pair_created_at": 1784280020.0, "fetched_at": 1784280764.006798}, "reason": "liquidity 20,412 < 25,000"}, {"snapshot": {"address": "3DWGb5wsipHWxTHxS3weBX6sKZw9ivJka2HXSVszh4RR", "symbol": "Slopped", "name": "Slopped", "chain": "solana", "pair_address": "DSCby8cay5F4kpPm1A6JmLUD5JH1a95ffFtFAiS93pqt", "dex": "meteora", "price_usd": 3.705e-05, "price_native": 4.958e-07, "liquidity_usd": 17888.54, "fdv_usd": 37051.0, "market_cap_usd": 37051.0, "volume_h1": 232790.53, "volume_h24": 232790.53, "price_change_m5": 97.37, "price_change_h1": 459.0, "price_change_h6": 459.0, "price_change_h24": 459.0, "buys_h1": 2418, "sells_h1": 401, "buys_m5": 146, "sells_m5": 136, "pair_created_at": 1784279965.0, "fetched_at": 1784280764.0068748}, "reason": "liquidity 17,889 < 25,000"}, {"snapshot": {"address": "HtuCPcNuuEMuoTSBAFfyFRvu3BzJ3kRgr5WiWQyZpump", "symbol": "WangWang", "name": "Justice for Wang Wang", "chain": "solana", "pair_address": "FrQH6MHKWxp6soCb5rg6JeZS7Vrem3vyDh8JKWAg5Kea", "dex": "pumpswap", "price_usd": 2.61e-05, "price_native": 3.495e-07, "liquidity_usd": 11914.83, "fdv_usd": 26103.0, "market_cap_usd": 26103.0, "volume_h1": 222891.94, "volume_h24": 222891.94, "price_change_m5": -32.1, "price_change_h1": -15.92, "price_change_h6": -15.92, "price_change_h24": -15.92, "buys_h1": 3587, "sells_h1": 3581, "buys_m5": 172, "sells_m5": 128, "pair_created_at": 1784277287.0, "fetched_at": 1784280761.544011}, "reason": "liquidity 11,915 < 25,000"}, {"snapshot": {"address": "7z5KZpYj7BEnGKGCY3kDkaX32ueBSNp8QjvFq8Lxpump", "symbol": "\u65fa\u65fa", "name": "Justice for Wang Wang", "chain": "solana", "pair_address": "32e137c8cuzq3i43xJXZvM2z46d5mABCgeLcUXQhURsp", "dex": "pumpswap", "price_usd": 3.433e-05, "price_native": 4.597e-07, "liquidity_usd": 13693.85, "fdv_usd": 34333.0, "market_cap_usd": 34333.0, "volume_h1": 209853.9, "volume_h24": 209853.9, "price_change_m5": -7.54, "price_change_h1": 10.58, "price_change_h6": 10.58, "price_change_h24": 10.58, "buys_h1": 3145, "sells_h1": 3196, "buys_m5": 110, "sells_m5": 91, "pair_created_at": 1784277248.0, "fetched_at": 1784280765.76445}, "reason": "liquidity 13,694 < 25,000"}, {"snapshot": {"address": "B4ptaVsUe6YbtBwAS38WFeweSrVNfQLCcj9JRrtjU8vn", "symbol": "SOLdiers", "name": "SOLdiers", "chain": "solana", "pair_address": "B4JM2z5DAqNCJtSFm4F8v5pc88KA8Fk3oyCSwEfsq9bR", "dex": "pumpswap", "price_usd": 0.00116, "price_native": 1.553e-05, "liquidity_usd": 125135.46, "fdv_usd": 1160835.0, "market_cap_usd": 1160835.0, "volume_h1": 189049.94, "volume_h24": 2973056.42, "price_change_m5": -1.46, "price_change_h1": -0.27, "price_change_h6": 42.81, "price_change_h24": -24.32, "buys_h1": 1044, "sells_h1": 930, "buys_m5": 25, "sells_m5": 13, "pair_created_at": 1784122840.0, "fetched_at": 1784280766.864652}, "reason": "score 48 < 60"}, {"snapshot": {"address": "J4idgExTUcrgJkrMazz1wU9PCRZhsoS2YkvKFGyfkCLe", "symbol": "5", "name": "San, Komorebi, nagi, Haku, Bono", "chain": "solana", "pair_address": "5ShEEKkyaRi5CHzeZfnwJGPGApe9U1tDAJ5LuicYZDzG", "dex": "meteora", "price_usd": 3.247e-05, "price_native": 4.346e-07, "liquidity_usd": 62777.81, "fdv_usd": 32478.0, "market_cap_usd": 32478.0, "volume_h1": 180315.82, "volume_h24": 180315.82, "price_change_m5": 0.61, "price_change_h1": 7.23, "price_change_h6": 7.23, "price_change_h24": 7.23, "buys_h1": 2220, "sells_h1": 1190, "buys_m5": 520, "sells_m5": 495, "pair_created_at": 1784280102.0, "fetched_at": 1784280763.209729}, "reason": "mcap 32,478 out of range"}, {"snapshot": {"address": "5hJUicZb1uZSwuYmsmo1uXZp41sJcNo7mvKjQDgbkADF", "symbol": "WangWang", "name": "Justice for Wang Wang", "chain": "solana", "pair_address": "8mcmZ6ZW4pgS8aokJUJXFfQnzsXaMU8sbcN2k77wZbeN", "dex": "pumpswap", "price_usd": 5.014e-05, "price_native": 6.715e-07, "liquidity_usd": 17330.51, "fdv_usd": 50142.0, "market_cap_usd": 50142.0, "volume_h1": 166692.73, "volume_h24": 166692.73, "price_change_m5": 577.0, "price_change_h1": 577.0, "price_change_h6": 577.0, "price_change_h24": 577.0, "buys_h1": 1013, "sells_h1": 185, "buys_m5": 1013, "sells_m5": 185, "pair_created_at": 1784280585.0, "fetched_at": 1784280760.7178051}, "reason": "liquidity 17,331 < 25,000"}, {"snapshot": {"address": "EJRF8jUTY97DaTt5dyas28REfjQvPrxDaHNyHiQu9Vog", "symbol": "\u65fa\u65fa", "name": "Justice for Wang Wang", "chain": "solana", "pair_address": "123tiqj5RfrBpoTL4TggdPecWGo7PE7bKT5o6DRxDTxy", "dex": "meteora", "price_usd": 3.99e-05, "price_native": 5.34e-07, "liquidity_usd": 15010.67, "fdv_usd": 39906.0, "market_cap_usd": 39906.0, "volume_h1": 134988.54, "volume_h24": 134988.54, "price_change_m5": 0.02, "price_change_h1": 523.0, "price_change_h6": 523.0, "price_change_h24": 523.0, "buys_h1": 2208, "sells_h1": 226, "buys_m5": 104, "sells_m5": 124, "pair_created_at": 1784280247.0, "fetched_at": 1784280762.3325598}, "reason": "liquidity 15,011 < 25,000"}, {"snapshot": {"address": "8CJNy8NGRpGVMKw1SnHoZBU8tc7Tz6yNUb7Aa49ZaXH5", "symbol": "\u65fa\u65fa", "name": "Justice for Wang Wang", "chain": "solana", "pair_address": "4GBmu3tD6zabSt2Fj11LdPn1fDBebtpS2CTVWbpZ59fn", "dex": "meteora", "price_usd": 5.502e-05, "price_native": 7.364e-07, "liquidity_usd": 15707.81, "fdv_usd": 55026.0, "market_cap_usd": 55026.0, "volume_h1": 133982.85, "volume_h24": 133982.85, "price_change_m5": -2.28, "price_change_h1": 677.0, "price_change_h6": 677.0, "price_change_h24": 677.0, "buys_h1": 1365, "sells_h1": 242, "buys_m5": 729, "sells_m5": 138, "pair_created_at": 1784280221.0, "fetched_at": 1784280762.332619}, "reason": "liquidity 15,708 < 25,000"}, {"snapshot": {"address": "E7vTVLLaxV3y68cpnDx2Q7ExeznhWgJKwPziKDsrpump", "symbol": "HOMIE", "name": "Welcome Back Homie", "chain": "solana", "pair_address": "5fg5azit5ed8PaZ12vdtTTMGXw5moNsutYXJWA2w6qDY", "dex": "pumpswap", "price_usd": 0.0002618, "price_native": 3.506e-06, "liquidity_usd": 45850.24, "fdv_usd": 261842.0, "market_cap_usd": 261842.0, "volume_h1": 116959.38, "volume_h24": 4709223.04, "price_change_m5": 3.64, "price_change_h1": 32.27, "price_change_h6": -38.98, "price_change_h24": -57.07, "buys_h1": 859, "sells_h1": 1343, "buys_m5": 65, "sells_m5": 99, "pair_created_at": 1784179220.0, "fetched_at": 1784280761.928123}, "reason": "buy/sell ratio 0.64 weak"}, {"snapshot": {"address": "6W1ycBgawCcRnjy2santpMBkQk9aHYvhvKLvgC5C63r9", "symbol": "5", "name": "San, Komorebi, nagi, Haku, Bono", "chain": "solana", "pair_address": "3bHDHvNsX4FDNEhGrgzKbUZ9pUcbdCPv8Ych3acZSVda", "dex": "pumpswap", "price_usd": 8.609e-06, "price_native": 1.155e-07, "liquidity_usd": 0.0, "fdv_usd": 8609.0, "market_cap_usd": 8609.0, "volume_h1": 104208.41, "volume_h24": 104208.41, "price_change_m5": 0.0, "price_change_h1": 10.75, "price_change_h6": 10.75, "price_change_h24": 10.75, "buys_h1": 2486, "sells_h1": 1240, "buys_m5": 0, "sells_m5": 0, "pair_created_at": 1784278779.0, "fetched_at": 1784280763.209735}, "reason": "liquidity 0 < 25,000"}, {"snapshot": {"address": "CsB957Ca4ZWVLBk7iHMfscmstK6cWuXrtxz82yZRWQ3U", "symbol": "WangWang", "name": "Justice for Wang Wang", "chain": "solana", "pair_address": "CbvM4KD18VjpbXfLXAmMcp8tJnWEvqybV5VucVFgddDF", "dex": "meteora", "price_usd": 1.08e-05, "price_native": 1.449e-07, "liquidity_usd": 2.16, "fdv_usd": 10803.0, "market_cap_usd": 10803.0, "volume_h1": 100551.07, "volume_h24": 100551.07, "price_change_m5": 0.0, "price_change_h1": 74.61, "price_change_h6": 74.61, "price_change_h24": 74.61, "buys_h1": 491, "sells_h1": 198, "buys_m5": 0, "sells_m5": 0, "pair_created_at": 1784279799.0, "fetched_at": 1784280764.403171}, "reason": "liquidity 2 < 25,000"}, {"snapshot": {"address": "9cRCn9rGT8V2imeM2BaKs13yhMEais3ruM3rPvTGpump", "symbol": "ANSEM", "name": "The Black Bull", "chain": "solana", "pair_address": "FnzKY6x7entQ1eR3D225dQyT7ybfka4PskBMQhb8L3CC", "dex": "pumpswap", "price_usd": 0.1882, "price_native": 0.002518, "liquidity_usd": 1949741.49, "fdv_usd": 188194228.0, "market_cap_usd": 188194228.0, "volume_h1": 96758.42, "volume_h24": 11544860.45, "price_change_m5": 0.05, "price_change_h1": -1.77, "price_change_h6": 4.86, "price_change_h24": 15.64, "buys_h1": 210, "sells_h1": 177, "buys_m5": 12, "sells_m5": 47, "pair_created_at": 1781643948.0, "fetched_at": 1784280766.864637}, "reason": "mcap 188,194,228 out of range"}, {"snapshot": {"address": "cqcmYVJajiR8KVKG1kwg2j7BjxrDLuWP39yvSEGE2Pd", "symbol": "5", "name": "San, Komorebi, nagi, Haku, Bono", "chain": "solana", "pair_address": "n2NggaWYGssemKVc2pU8vjYqfZY9ugX7tryMsxfZBC5", "dex": "meteora", "price_usd": 3.222e-05, "price_native": 4.323e-07, "liquidity_usd": 9.55, "fdv_usd": 32224.0, "market_cap_usd": 32224.0, "volume_h1": 95877.86, "volume_h24": 95877.86, "price_change_m5": 0.0, "price_change_h1": 6.38, "price_change_h6": 6.38, "price_change_h24": 6.38, "buys_h1": 1635, "sells_h1": 634, "buys_m5": 0, "sells_m5": 0, "pair_created_at": 1784279652.0, "fetched_at": 1784280765.29285}, "reason": "liquidity 10 < 25,000"}, {"snapshot": {"address": "gTEcVtvYRFXo8AfBPqhq67f9mqxUkV19RQBE6KQvJq6", "symbol": "VORF", "name": "Vanguard Oil Retirement Fund", "chain": "solana", "pair_address": "4fCHTpGpbejkympYfmz3DTohH22q1XHntAXkdtGZdEq3", "dex": "pumpswap", "price_usd": 0.0004016, "price_native": 5.379e-06, "liquidity_usd": 0.0, "fdv_usd": 401622.0, "market_cap_usd": 401622.0, "volume_h1": 94907.76, "volume_h24": 94907.76, "price_change_m5": 14.09, "price_change_h1": 119.0, "price_change_h6": 119.0, "price_change_h24": 119.0, "buys_h1": 1293, "sells_h1": 1158, "buys_m5": 84, "sells_m5": 70, "pair_created_at": 1784279038.0, "fetched_at": 1784280761.131222}, "reason": "liquidity 0 < 25,000"}, {"snapshot": {"address": "rkbX3fimkB2fPBKopYkSx82xSuWdUbNBuNuw7efpump", "symbol": "GOATBATH", "name": "GOAT Bath", "chain": "solana", "pair_address": "Fyy9bLRMvNeosh8R1ZF4SXkxWvDLXc7nXaSk4YBPZgoA", "dex": "pumpswap", "price_usd": 0.0003688, "price_native": 4.939e-06, "liquidity_usd": 47930.05, "fdv_usd": 368808.0, "market_cap_usd": 368808.0, "volume_h1": 88875.32, "volume_h24": 1174217.87, "price_change_m5": 1.38, "price_change_h1": 7.96, "price_change_h6": 24686.0, "price_change_h24": 707.0, "buys_h1": 1008, "sells_h1": 1610, "buys_m5": 122, "sells_m5": 321, "pair_created_at": 1784206327.0, "fetched_at": 1784280761.5440068}, "reason": "already pumped 707% in 24h"}, {"snapshot": {"address": "4ue4ws9WB9ZEWYzCdG68APo2jHciSFbBEeQi6fMSpump", "symbol": "16", "name": "back when i was 16 in the bronx", "chain": "solana", "pair_address": "49FDNFWALo8mAPCaQnaeZdPeVqjSAEaMdUc9LU7mJeyp", "dex": "pumpfun", "price_usd": 7.595e-06, "price_native": 1.016e-07, "liquidity_usd": 0.0, "fdv_usd": 7595.57, "market_cap_usd": 7595.57, "volume_h1": 86583.96, "volume_h24": 86583.96, "price_change_m5": -53.18, "price_change_h1": 231.0, "price_change_h6": 231.0, "price_change_h24": 231.0, "buys_h1": 1405, "sells_h1": 1258, "buys_m5": 386, "sells_m5": 355, "pair_created_at": 1784279839.0, "fetched_at": 1784280764.40313}, "reason": "liquidity 0 < 25,000"}], "mode": "paper", "profile": "aggressive", "status": {"equity": 1000.0, "cash": 1000.0, "starting_cash": 1000.0, "wins": 0, "losses": 0, "fees": 0.0, "killed": false, "halted_for_day": false}, "positions": [], "dd_reports": {"EKpQGSJtjMFqKZ9KQanSqYXRcF8fBopzLHYxdM65zcjm": "WIF_EKpQGSJt.html", "TGTrnjkirTrmJwdrHZ9MRh4J46C8jFRMs3Ayyozpump": "smolcat_TGTrnjki.html", "5eAF5tC2BgjH9HF8XLKWjazgQU4KEL3ZqZXwRMSHpump": "CryingCat_5eAF5tC2.html", "DwA8xDTFt4aLujsHhW72LDYN5xsnFYsXLXVn1Guppump": "cat_DwA8xDTF.html", "9jTr8PmNX7eH9eK6aMG2MuYBzPZm16U7xhtHeaozBUwE": "ACCOUNT_9jTr8PmN.html", "6JmbvqA1zY8T1H6qEMqzrjwSBTq2Ba1kqkywcUHw135n": "ACCOUNT_6JmbvqA1.html", "5rnhCX1oqY4wDEJcsrgpjvzTE2a39hpLaqSgZkou2t1r": "ACCOUNT_5rnhCX1o.html", "2x2yf9NMapNFuBYgfpBi9rFv1vLdu34DvwcRxEyuTGKc": "ACCOUNT_2x2yf9NM.html", "Dh6h5yk7qSBeZkbucNvXMcLcNnMp1ssi6Hp5HxGZAKbD": "Incum_Dh6h5yk7.html", "DUdzLjTTNHx6yTrYzJorbvc3x5ascZKFwmifj16RGMtm": "Incum_DUdzLjTT.html", "Gg2xdFJc6j4pVavUSfwHKZ4RAbJpbMcGZMKwGUaBpBpR": "Incum_Gg2xdFJc.html", "47BBWaDy3ZatHghsBg7q7mnrtoLZGxRD3Umkjov8b4Qb": "PUMPVERSIT_47BBWaDy.html", "9aEn4rKoHLA3R4o58cPEVHGBWPJR6GjtrPv6D9vtNxQc": "Incum_9aEn4rKo.html", "2agcQWJftYzYWJNDW4BPok1RKL1xVqpDJtT4SSVVpump": "CS_2agcQWJf.html", "He6pECrSVi123qabQJRiGEonMbBZ7e8PZ9NmUxKqpump": "bet_He6pECrS.html", "HNg5PYJmtqcmzXrv6S9zP1CDKk5BgDuyFBxbvNApump": "ALCH_HNg5PYJm.html", "BBSEsu4v5wR9h2HsnxPbVJuCKsRe2Cx77c598dKbpump": "Bullish_BBSEsu4v.html", "DXS6UqB4xGJoy6VSQFJE54zGX16dfJH6uCvT7fB6EW29": "BullBit_DXS6UqB4.html", "DKmJw1U4R8xHoU7Qk1R2npfD3cdyfTXmH2jcgyi1pump": "BullBit_DKmJw1U4.html", "9cRCn9rGT8V2imeM2BaKs13yhMEais3ruM3rPvTGpump": "ANSEM_9cRCn9rG.html", "7V6Sk63y8Rr1MvcN5mYNp61wgFhy4EeQg5gUASk9pump": "HBULL_7V6Sk63y.html", "G9j8WWDeJXZdvwQgP82ooDuHmpc3Gy8NCSins71Lpump": "BULLCAT_G9j8WWDe.html", "5Lvs7V6AJhUgyAW5LTJVz46Z23kUqMaTMpWDCD1NEZHC": "PUDGY_5Lvs7V6A.html", "21qCC71G59QASc7aTU7GYFhy7WifpmP8PX9tDhWosHZz": "PUDGY_21qCC71G.html", "ANhYwVbHvsxpLFZSYujvz9jEyFoNWqmMpAT4oUEC6ith": "PUDGY_ANhYwVbH.html", "2E1bcZmYuNy7fbfwJzcJGT578PhBJaJNqQ7PwwX7ZAiZ": "CHYNA_2E1bcZmY.html", "DtAvZU6K4bitFevYXPxwD929myw2PbvJbJPeMJjnsQ7W": "CHYNA_DtAvZU6K.html", "8pStW6495TdRFHrf5Jc1cJgLLqYLMPJqXgXbmbbtB371": "CHYNA_8pStW649.html", "BQK9FSFEuj7ibuT6VLnZGUe5NWRDnKCwnqQvxBzCJs2K": "FORGE_BQK9FSFE.html", "FmVtrnVsMLgpZhxxoTmh7MH43mon4jzpU5G4HzSvHGcf": "FORGE_FmVtrnVs.html", "RPC8MbAndTBJ56nT25GkD7ZT38xsKjD6Ybo94HHJggF": "FORGE_RPC8MbAn.html", "Hwi9LHXUkzM8sA8TRP3WZqybYiMJNFhutQBNRHpPkG9A": "CASHCOW_Hwi9LHXU.html", "5yBMRg1GttnPRR5X7xZw7Ap8L77YJ1EKi11VSbmyncyQ": "ASHCAT_5yBMRg1G.html", "7isZrjW57hUMpZbmcGEfBmopXArG2y1j5ueo5Q3eY13o": "blepcat_7isZrjW5.html", "BkrQMrnvZrvkRrF3ZDqSWU4NA6GEQFB2H7toquAdZPCB": "ALON_BkrQMrnv.html", "3b9hPbPL8F4xt3Gv2qFsMLNxUfPxzkVvv56MxAuswHvH": "ALON_3b9hPbPL.html", "HtBLByMW8KTfXRFcUZuq5iYkGFSoDBdg8R1kfthZNnHh": "ALON_HtBLByMW.html", "DmLiYtFmh7M3M3qnPoQoxkSup766u7KAUv3Ba57WMuny": "CASHCOW_DmLiYtFm.html", "5E7uSHMiZJMkG4phQpEp9M1musVYi5K9F9ZTGrEeUGat": "SPAIN_5E7uSHMi.html", "CzhariFmXDsgcpW5RBbkmE751MMKHcXxmX7yMW2p3Fj6": "RETAIL_CzhariFm.html", "E3Yr12sz4VB8uKb6DjFM1c6uLZ7hcyRi2UtBFqMbdqW4": "trmp_E3Yr12sz.html", "3efEwcj5txVWRWn8Qa8A4vHA7UUAGr4poCM2Hzxxx6nq": "TrumpButt_3efEwcj5.html", "2pDipdYtgCpkTRHgLx4FTohrn9kWp7NJy8nqLbv5Yw13": "TRUMPCOIN_2pDipdYt.html", "8dByMMXkyNejYQzsxdA17BCkkQQHS47UQPvCroMrwV7o": "ALON_8dByMMXk.html", "26ArUrCANdyA1wPPT3Bu3Zxk7xCiLfuhVvu6wesqq9SD": "TrumpCoin_26ArUrCA.html", "3RsQxn41WHJBjbskX2n81SgJQzu6syP4qaLgEz1xwxES": "ANSEM_3RsQxn41.html", "DUyxZyYjmzTJ43N7u6Z8sBn8UUfJrx4fLgELbgzmt2hL": "BULLY_DUyxZyYj.html", "Da7eRGAdrc5wZ7dN7qHJEcftxy79NYcst19Fz72Rd4Bh": "LIKWELI_Da7eRGAd.html", "AuzNJJLoVb52CiKggafAC8hdejyXQG8FJL3VoMmwcN4K": "LIKWELI_AuzNJJLo.html", "ATHCTt8EnJNnkqLFG9mYPnY8XgGGU8jFjR4zfHvBqLLe": "CASHCOW_ATHCTt8E.html", "8zx1iTfXqrZp9Kke2gzMGEBqfwaGhvKJVjt1t6kvgeom": "CEO_8zx1iTfX.html", "Cu5ph21J9u2NR5tVsU7BxYs9Vju7gpakE7fgo7epAH5h": "ANSEM_Cu5ph21J.html", "mNhTPQgwuP6rvXVSFG5uyL1NhbtMH9g3Q22HwNknTJt": "CASHCOW_mNhTPQgw.html", "2n2kMamVr5yAfmg5YFJnUro6JB858Ko6KqEfkaLNxk1R": "The_2n2kMamV.html", "EVbXayw9HEmhuRcaQVoTCiHiCeEtM39Bw9TfeVmrpump": "KYLE_EVbXayw9.html", "EFzoP4moGS2nTJqAU9u2V8PGj6tUBk3GSndWpLtrM8TB": "CASHCOW_EFzoP4mo.html", "H2i8dXoYZUMAgrVu36UiSexstBGGS5KfQjpZzEWZ1TFj": "Clownlana_H2i8dXoY.html", "3gCbnfSJ2XRT7VT7jMBnovVtNT85vEhxpvmiAMaHjZE7": "Hook_3gCbnfSJ.html", "EMkMkWLuMS7XLsaTrZUCcsAZMxQAEqd9W4EtMZvtG7Hi": "TOKEN_EMkMkWLu.html", "5jyRXUGTkCCJDRVhHJELVSv4uAcsFJykCB8Cf8wbVeDB": "TOKEN_5jyRXUGT.html", "8CVhS1FSZM6wBmbdiZZeGkRRigu8c74uiZLi9yxDKvzS": "TOKEN_8CVhS1FS.html", "3rYV2AoyqhJJcaGRTEK7DcpXR85GiSDshftioMKKhjqc": "CHILL_3rYV2Aoy.html", "HZAgEd4LTbTbNLn8dEpLLBNN8ydUuWuK3PB4JoKwTQYp": "CHILL_HZAgEd4L.html", "5Lo1rzmKNAn14FCZqfQQybyBkGvN3E9xCu5smK8TGvc4": "CHILL_5Lo1rzmK.html", "itQeBVnCY9U2fUwrKSi7D2Xcq46ZMaKsPfacmxJpump": "URKL_itQeBVnC.html", "HVRtNeFPrDcAA9Yu3WrTEdCsTLGJiYDiQbqjg3efpump": "CUBEMAN_HVRtNeFP.html", "G9VVud86SLgb7SnTqRKXJVUkzwLzCf4R89vknWVKbonk": "Trump_Coin_G9VVud86.html", "D6ytjMdBBPoV8nsRHJhvrkpwF7sgVBYd7PufkRHNpump": "CASHCOW_D6ytjMdB.html", "7z5KZpYj7BEnGKGCY3kDkaX32ueBSNp8QjvFq8Lxpump": "\u65fa\u65fa_7z5KZpYj.md", "BtsW2oWyBMSCwXmyTFafEkhc9xTtJBDphdQ2tMCvD3g7": "URKL_BtsW2oWy.html", "Ezx6F3g2f92p86wv9vb5Tw6q8bFXFdtUQHDZs7qzWRYH": "TOKEN_Ezx6F3g2.html", "9JtVEmpJhi1tXb5pGzi2ZCC9qHaxuVs3TiMKAT5ghNQc": "WangWang_9JtVEmpJ.html", "5yJgw6a8bb1nRsmEBr6vzX5pt6sQekzqG9nfmxqMpump": "PROPHECY_5yJgw6a8.html", "CZSJaDpGigeprcSvdmtq3ePQPo3ZNYJeNoEvMDxBpump": "MENSAHOOD_CZSJaDpG.html", "4AzQbJYUAqyQPPXMDvy7yZWTMErHYdmDFGMVYeqm2DCv": "HOOD_4AzQbJYU.html", "HBWfbvbRvFQuw3X1PpmVeBKNpm5eFyKpYpB6jUDSvRjT": "MENSAHOOD_HBWfbvbR.html", "CFPkPq1eYPR8GLzEo59wUbbMioX4bshaTQiSGzTSpump": "MENSA_CFPkPq1e.html", "2u6Dq88YjY2Ff1RexGN4dNp51T9bFvAYsY1CVYi8dUej": "BLACKCAT_2u6Dq88Y.html", "GTG8JYafTa3DzzZUUN1RHNdyVDEzMDBuqDMq3aJvpump": "SMIRKCAT_GTG8JYaf.html", "496xCvJ4KGCzCRSSmYZ4H7stdkwEQUBEbBsHdnqKpd7F": "TOKEN_496xCvJ4.html", "EcCjMAJEXcBMZ5QWtX4PKUkpSvoEFdcs41MKcXjwMEbu": "Princess_EcCjMAJE.html"}, "trades": []}